Workbook

Sheet Read Me
A1: HR Health Check | risk and action build pack
A2: V3 develops the existing workbook rather than replacing its structure. The customer sees a clear assessment and action plan; the additional detail is the controlled content and logic behind it.
A3: DREAMSTONEHR | PROPOSED V3.0 | 10 OCTOBER 2026
A5: Section | B5: Decision / guidance | C5: Where to work
A6: Purpose | B6: A paid, self-reported HR decision-support assessment for businesses with 5-200 employees. Give a useful plan without requiring a second purchase. | C6: Client Preview
A7: What changed in v3 | B7: Retained 44 core questions; added three targeted conditional questions. All 69 questions now have five response pathways, risk reasoning and practical next steps. | C7: Questions; Answers; Answer Outcomes
A8: What was already present | B8: V2 had 66 questions, 330 answer choices, broad action triggers and useful first-step action cards. It did not yet provide the full response-specific risk and context layer now added. | C8: Original v2 workbook remains unchanged.
A9: Where to start | B9: Read Client Preview to see the intended outcome. Review Risk Method before changing ratings, then edit Questions, Answers and Action Library for content. | C9: Client Preview; Risk Method
A10: Question catalogue | B10: 44 core plus 25 conditional questions; eight additional unscored context prompts are routed and reused by workstream, not repeated per finding. | C10: Profile & Routes; Risk Context
A11: Customer outcome | B11: What was reported; the concern and reason; provisional risk; action priority; practical steps; owner; relevant timing; completion evidence; recheck trigger. | C11: Answer Outcomes; Risk Register
A12: Score versus risk | B12: The reported-practice score remains separate from risk and urgency. An unresolved essential element can stay High even where the answer earns partial points. | C12: Scoring; Risk Method
A13: Unknown is different | B13: DK receives no demonstrated practice points and remains in the eligible denominator, as in v2. Risk is Unverified; verification can still be High priority. | C13: Answers; Risk Method
A14: Rating status | B14: Low / Medium / High / Critical are proposed triage ratings. Actual likelihood, legal compliance, WHS risk and residual-risk reduction are not established by this questionnaire. | C14: Risk Method; Sources
A15: Timeframe safeguard | B15: Two business days, 30 days and 90 days are proposed response/planning targets, never grace periods. Current harm and earlier duties, decisions or deadlines take precedence. | C15: Risk Method
A16: Working demonstration | B16: Edit Score Sandbox F/G for eligibility and responses. In Risk Register, G:K adds scoped context. Client Preview then changes through formulas. Defaults are fictional. | C16: Score Sandbox; Risk Register
... A24: Original traceability | B24: Current Review and Original Options preserve the original question review and source options. Historical test results are labelled as v2, not claims of v3 validation. | C24: Current Review; Original Options

Sheet Client Preview
A1: Your HR priorities | illustrative report preview
A2: Fictional example driven by Score Sandbox and Risk Register. Read the actions before the score. Ratings reflect reported practices and context, not an independent audit or a finding that the business has breached the law.
A5: Overall position | C5: ='Score Sandbox'!K19 -> Priority review required
A6: Reported-practice score | C6: =IF(ISNUMBER('Score Sandbox'!F21),TEXT('Score Sandbox'!F21,"0.0")&" / 100. This is not a compliance percentage.","Withheld until information or configuration is resolved") -> 91.0 / 100. This is not a compliance percentage.
A7: Risk and action alerts | C7: =COUNTIF('Risk Register'!$N$6:$N$74,4)&" Critical action(s); "&COUNTIF('Risk Register'!$N$6:$N$74,3)&" High-priority action(s). Risk may remain Unverified where the task is to confirm information." -> 0 Critical action(s); 4 High-priority action(s). Risk may remain Unverified where the task is to confirm information.
A8: Unknown information | C8: =TEXT('Score Sandbox'!H19,"0.0%")&" of the domain-weighted assessment is not yet confirmed. Unknown is not the same as absent or unlawful." -> 3.2% of the domain-weighted assessment is not yet confirmed. Unknown is not the same as absent or unlawful.
A9: Immediate safety notice | C9: =IF(COUNTIF('Risk Register'!$G$6:$G$74,"LIVE_HARM")>0,"A serious current exposure has been reported. Take appropriate protective action and seek urgent help now. Do not wait for this assessment to be completed.","No immediate-harm override is selected in this demonstration. This does not establish that the workplace is free of immediate hazards.") -> No immediate-harm override is selected in this demonstration. This does not establish that the workplace is free of immediate hazards.
A11: Critical and High-priority alerts
A12: Priority 1 | C12: =IF($J$12=0,"",IF(INDEX('Risk Register'!$N$6:$N$74,$J$12)<3,"",INDEX('Risk Register'!$O$6:$O$74,$J$12)&" priority | "&INDEX('Risk Register'!$M$6:$M$74,$J$12)&" risk | "&INDEX('Risk Register'!$P$6:$P$74,$J$12))) -> High priority | High risk | Test the payroll result, not just the base rate | J12: =IFERROR(MATCH(1,'Risk Register'!$AA$6:$AA$74,0),0) -> 2
A13: Priority 2 | C13: =IF($J$13=0,"",IF(INDEX('Risk Register'!$N$6:$N$74,$J$13)<3,"",INDEX('Risk Register'!$O$6:$O$74,$J$13)&" priority | "&INDEX('Risk Register'!$M$6:$M$74,$J$13)&" risk | "&INDEX('Risk Register'!$P$6:$P$74,$J$13))) -> High priority | High risk | Reduce reliance on one person | J13: =IFERROR(MATCH(2,'Risk Register'!$AA$6:$AA$74,0),0) -> 29
A14: Priority 3 | C14: =IF($J$14=0,"",IF(INDEX('Risk Register'!$N$6:$N$74,$J$14)<3,"",INDEX('Risk Register'!$O$6:$O$74,$J$14)&" priority | "&INDEX('Risk Register'!$M$6:$M$74,$J$14)&" risk | "&INDEX('Risk Register'!$P$6:$P$74,$J$14))) -> High priority | High risk | Make the reporting route work when power is involved | J14: =IFERROR(MATCH(3,'Risk Register'!$AA$6:$AA$74,0),0) -> 43
A15: Priority 4 | C15: =IF($J$15=0,"",IF(INDEX('Risk Register'!$N$6:$N$74,$J$15)<3,"",INDEX('Risk Register'!$O$6:$O$74,$J$15)&" priority | "&INDEX('Risk Register'!$M$6:$M$74,$J$15)&" risk | "&INDEX('Risk Register'!$P$6:$P$74,$J$15))) -> High priority | Unverified risk | Verify: confirm super reaches the fund | J15: =IFERROR(MATCH(4,'Risk Register'!$AA$6:$AA$74,0),0) -> 4
A16: Priority 5 | C16: =IF($J$16=0,"",IF(INDEX('Risk Register'!$N$6:$N$74,$J$16)<3,"",INDEX('Risk Register'!$O$6:$O$74,$J$16)&" priority | "&INDEX('Risk Register'!$M$6:$M$74,$J$16)&" risk | "&INDEX('Risk Register'!$P$6:$P$74,$J$16))) | J16: =IFERROR(MATCH(5,'Risk Register'!$AA$6:$AA$74,0),0) -> 1
A17: Priority 6 | C17: =IF($J$17=0,"",IF(INDEX('Risk Register'!$N$6:$N$74,$J$17)<3,"",INDEX('Risk Register'!$O$6:$O$74,$J$17)&" priority | "&INDEX('Risk Register'!$M$6:$M$74,$J$17)&" risk | "&INDEX('Risk Register'!$P$6:$P$74,$J$17))) | J17: =IFERROR(MATCH(6,'Risk Register'!$AA$6:$AA$74,0),0) -> 3
A18: Priority 7 | C18: =IF($J$18=0,"",IF(INDEX('Risk Register'!$N$6:$N$74,$J$18)<3,"",INDEX('Risk Register'!$O$6:$O$74,$J$18)&" priority | "&INDEX('Risk Register'!$M$6:$M$74,$J$18)&" risk | "&INDEX('Risk Register'!$P$6:$P$74,$J$18))) | J18: =IFERROR(MATCH(7,'Risk Register'!$AA$6:$AA$74,0),0) -> 6
A19: Priority 8 | C19: =IF($J$19=0,"",IF(INDEX('Risk Register'!$N$6:$N$74,$J$19)<3,"",INDEX('Risk Register'!$O$6:$O$74,$J$19)&" priority | "&INDEX('Risk Register'!$M$6:$M$74,$J$19)&" risk | "&INDEX('Risk Register'!$P$6:$P$74,$J$19))) | J19: =IFERROR(MATCH(8,'Risk Register'!$AA$6:$AA$74,0),0) -> 8
A21: Alert coverage | C21: =IF(COUNTIF('Risk Register'!$N$6:$N$74,">=3")>8,COUNTIF('Risk Register'!$N$6:$N$74,">=3")-8&" additional priority alerts are in Risk Register. This preview does not remove them.","Every Critical / High-priority alert in this example is shown above. The complete register also contains other improvements and maintenance.") -> Every Critical / High-priority alert in this example is shown above. The complete register also contains other improvements and maintenance.
A23: Start with these workstreams
A24: How to use the plan | C24: Choose an owner for each workstream. The lead finding is shown below; keep related findings as separate tasks within it. Complete urgent or legally required action before routine improvements. Suggested targets are not legal grace periods.
A26: Workstream 1 | J26: =IFERROR(MATCH(1,'Risk Register'!$AH$6:$AH$74,0),0) -> 2
A27: Lead finding | C27: =IF($J$26=0,"No further active workstream in this example",INDEX('Risk Register'!$P$6:$P$74,$J$26)) -> Test the payroll result, not just the base rate
A28: Risk / priority | C28: =IF($J$26=0,"",INDEX('Risk Register'!$M$6:$M$74,$J$26)&" provisional risk; "&INDEX('Risk Register'!$O$6:$O$74,$J$26)&" action priority. Basis: "&INDEX('Risk Register'!$K$6:$K$74,$J$26)) -> High provisional risk; High action priority. Basis: Self-report only
A29: Why it matters | C29: =IF($J$26=0,"No further active workstream in this example",INDEX('Risk Register'!$Q$6:$Q$74,$J$26)) -> An unchecked pay rule can repeat across pay periods and employees. The initial gap is lack of assurance, not proof of an underpayment.
A30: Do first | C30: =IF($J$26=0,"No further active workstream in this example",INDEX('Risk Register'!$R$6:$R$74,$J$26)) -> Replace the assumption with a current check. Select representative ordinary and exception pay periods and obtain the actual work records, applicable rules and payslips. Define the arrangements being checked before calculating any difference.
A31: Then | C31: =IF($J$26=0,"No further active workstream in this example",INDEX('Risk Register'!$S$6:$S$74,$J$26)) -> 1. Recalculate selected ordinary and exception pay periods using actual work records. Record differences by entitlement, period and affected arrangement. 2. Investigate the cause of each difference, extend the review where appropriate and test the next affected pay run after correction.
A32: Who owns it | C32: =IF($J$26=0,"No further active workstream in this example",INDEX('Risk Register'!$V$6:$V$74,$J$26)) -> Payroll lead / owner
A33: When to act | C33: =IF($J$26=0,"No further active workstream in this example",INDEX('Risk Register'!$W$6:$W$74,$J$26)) -> Review or verify within 2 business days, or before an earlier duty/event. Do not wait where harm or law requires immediate action.
A34: Finished means | C34: =IF($J$26=0,"No further active workstream in this example",INDEX('Risk Register'!$U$6:$U$74,$J$26)) -> A dated pay-check record for each materially different pay arrangement, with discrepancies investigated, required corrections completed and the next affected pay run checked. Keep any unresolved scope or payment issue open. Confirm that the change works in practice, not only that a document exists.
A35: You reported | C35: =IF($J$26=0,"",INDEX('Answer Outcomes'!$D$6:$D$350,INDEX('Risk Register'!$AF$6:$AF$74,$J$26))) -> We assume our software, payroll provider or above-award rates make the payments correct.
A36: Related findings | C36: =IF($J$26=0,"",INDEX('Risk Register'!$X$6:$X$74,$J$26)&": "&COUNTIFS('Risk Register'!$X$6:$X$74,INDEX('Risk Register'!$X$6:$X$74,$J$26),'Risk Register'!$N$6:$N$74,">1")&" active item(s) in this family. Use Risk Register to retain every child action and exception.") -> PAY_ASSURANCE: 1 active item(s) in this family. Use Risk Register to retain every child action and exception.
A37: Check again | C37: =IF($J$26=0,"No further active workstream in this example",INDEX('Risk Register'!$AC$6:$AC$74,$J$26)) -> A pay-rule change, payroll migration, discrepancy or new work pattern.
A39: Workstream 2 | J39: =IFERROR(MATCH(2,'Risk Register'!$AH$6:$AH$74,0),0) -> 29
A40: Lead finding | C40: =IF($J$39=0,"No further active workstream in this example",INDEX('Risk Register'!$P$6:$P$74,$J$39)) -> Reduce reliance on one person
A41: Risk / priority | C41: =IF($J$39=0,"",INDEX('Risk Register'!$M$6:$M$74,$J$39)&" provisional risk; "&INDEX('Risk Register'!$O$6:$O$74,$J$39)&" action priority. Basis: "&INDEX('Risk Register'!$K$6:$K$74,$J$39)) -> High provisional risk; High action priority. Basis: Self-report only
A42: Why it matters | C42: =IF($J$39=0,"No further active workstream in this example",INDEX('Risk Register'!$Q$6:$Q$74,$J$39)) -> If essential work depends on one unavailable person, payroll, client delivery or approvals can stop even when the rest of the team is capable.
A43: Do first | C43: =IF($J$39=0,"No further active workstream in this example",INDEX('Risk Register'!$R$6:$R$74,$J$39)) -> Replace the assumption with a current check. Choose one business-critical task with no tested backup. Document the essentials and have the nominated backup perform a supervised run-through.
A44: Then | C44: =IF($J$39=0,"No further active workstream in this example",INDEX('Risk Register'!$S$6:$S$74,$J$39)) -> 1. Name a capable backup or external alternative and prepare secure, usable instructions for the critical task. 2. Test the backup without relying on the usual person. Record what failed and retest it.
A45: Who owns it | C45: =IF($J$39=0,"No further active workstream in this example",INDEX('Risk Register'!$V$6:$V$74,$J$39)) -> Owner / people manager
A46: When to act | C46: =IF($J$39=0,"No further active workstream in this example",INDEX('Risk Register'!$W$6:$W$74,$J$39)) -> Review or verify within 2 business days, or before an earlier duty/event. Do not wait where harm or law requires immediate action.
A47: Finished means | C47: =IF($J$39=0,"No further active workstream in this example",INDEX('Risk Register'!$U$6:$U$74,$J$39)) -> A tested cover arrangement for priority tasks, including secure access and authorisations. Confirm that the change works in practice, not only that a document exists.
A48: You reported | C48: =IF($J$39=0,"",INDEX('Answer Outcomes'!$D$6:$D$350,INDEX('Risk Register'!$AF$6:$AF$74,$J$39))) -> We rely on that person explaining the work if they become unavailable.
A49: Related findings | C49: =IF($J$39=0,"",INDEX('Risk Register'!$X$6:$X$74,$J$39)&": "&COUNTIFS('Risk Register'!$X$6:$X$74,INDEX('Risk Register'!$X$6:$X$74,$J$39),'Risk Register'!$N$6:$N$74,">1")&" active item(s) in this family. Use Risk Register to retain every child action and exception.") -> CAPABILITY: 1 active item(s) in this family. Use Risk Register to retain every child action and exception.
A50: Check again | C50: =IF($J$39=0,"No further active workstream in this example",INDEX('Risk Register'!$AC$6:$AC$74,$J$39)) -> Key leave, resignation, changed systems or a failed continuity test.
A52: Workstream 3 | J52: =IFERROR(MATCH(3,'Risk Register'!$AH$6:$AH$74,0),0) -> 43
A53: Lead finding | C53: =IF($J$52=0,"No further active workstream in this example",INDEX('Risk Register'!$P$6:$P$74,$J$52)) -> Make the reporting route work when power is involved
A54: Risk / priority | C54: =IF($J$52=0,"",INDEX('Risk Register'!$M$6:$M$74,$J$52)&" provisional risk; "&INDEX('Risk Register'!$O$6:$O$74,$J$52)&" action priority. Basis: "&INDEX('Risk Register'!$K$6:$K$74,$J$52)) -> High provisional risk; High action priority. Basis: Self-report only
A55: Why it matters | C55: =IF($J$52=0,"No further active workstream in this example",INDEX('Risk Register'!$Q$6:$Q$74,$J$52)) -> A reporting route can fail precisely when the concern involves the person controlling it, leaving the business without a credible way to hear and address the issue.
A56: Do first | C56: =IF($J$52=0,"No further active workstream in this example",INDEX('Risk Register'!$R$6:$R$74,$J$52)) -> Identify who could receive a concern when the owner, manager or usual contact is involved, and whether that person has the authority and independence needed to arrange an appropriate response.
A57: Then | C57: =IF($J$52=0,"No further active workstream in this example",INDEX('Risk Register'!$S$6:$S$74,$J$52)) -> 1. Name an alternative recipient without a relevant conflict and document escalation, confidentiality boundaries and protection from retaliation. 2. Explain the route to staff, test a fictional owner-related concern and check that the recipient can arrange an appropriate response.
A58: Who owns it | C58: =IF($J$52=0,"No further active workstream in this example",INDEX('Risk Register'!$V$6:$V$74,$J$52)) -> Business leader / safety lead
A59: When to act | C59: =IF($J$52=0,"No further active workstream in this example",INDEX('Risk Register'!$W$6:$W$74,$J$52)) -> Review or verify within 2 business days, or before an earlier duty/event. Do not wait where harm or law requires immediate action.
A60: Finished means | C60: =IF($J$52=0,"No further active workstream in this example",INDEX('Risk Register'!$U$6:$U$74,$J$52)) -> Staff can identify and use a credible alternative route when the normal contact is involved, the recipient can arrange an appropriate response, and confidentiality and protection-from-retaliation safeguards have been tested. Confirm that the change works in practice, not only that a document exists.
A61: You reported | C61: =IF($J$52=0,"",INDEX('Answer Outcomes'!$D$6:$D$350,INDEX('Risk Register'!$AF$6:$AF$74,$J$52))) -> There is no credible route for that situation.
A62: Related findings | C62: =IF($J$52=0,"",INDEX('Risk Register'!$X$6:$X$74,$J$52)&": "&COUNTIFS('Risk Register'!$X$6:$X$74,INDEX('Risk Register'!$X$6:$X$74,$J$52),'Risk Register'!$N$6:$N$74,">1")&" active item(s) in this family. Use Risk Register to retain every child action and exception.") -> RESPECT: 1 active item(s) in this family. Use Risk Register to retain every child action and exception.
A63: Check again | C63: =IF($J$52=0,"No further active workstream in this example",INDEX('Risk Register'!$AC$6:$AC$74,$J$52)) -> Changed ownership or reporting contacts, a conflict or concern about retaliation.
A66: No priority finding is removed by the short list
A67: Full risk register | C67: Open the complete Risk Register, including every Critical / High action and verification task.
A68: Completion safeguard | C68: Creating a policy, booking training or marking a task complete does not automatically lower a risk. Check that the change is implemented and works, preserve the earlier finding, then reassess.
A69: Independent value | C69: The reasons, steps and completion evidence are available without a further purchase. DreamStoneHR support is an option for interpretation, specialist checks or implementation, not a condition of using the plan.
A70: Scope and limitations | C70: This is a build-stage illustration, not a full rendered customer report. The implemented report must also show the selected responses, applicable scope, all High/Critical alerts, all unresolved questions, source links and any relevant actual dates.

Sheet Questions
A1: Question library | retained core, targeted additions
A2: 44 core questions and 25 conditional questions. Stable IDs retain traceability. Risk consequence is a proposed design judgement, separate from question weight and actual likelihood.
A3: DREAMSTONEHR | PROPOSED V3.0 | 10 OCTOBER 2026
A5: Question ID | B5: Domain | C5: Category | D5: Question | E5: Route | F5: Weight | G5: Critical flag | H5: Answer model | I5: Optional help / interpretation | J5: Original IDs | K5: Action ID | L5: Action family | M5: Source IDs | N5: Primary source URLs | O5: Risk type | P5: Potential consequence class | Q5: Partial answer remains High? | R5: Version note
A6: PAY01 | B6: PAY | C6: Pay & Entitlements | D6: How has your business established which employment rules and classifications apply to each role? | E6: ALL | F6: 3 | G6: Yes | H6: Single choice: 0-3 / DK | I6: Think about the applicable employment system, award or enterprise agreement, and actual duties. A job title or an above-award salary is not enough to decide coverage. | J6: Q01;Q03 | K6: A_PAY01 | L6: PAY_ASSURANCE | M6: S06;S14 | N6: https://www.fairwork.gov.au/pay-and-wages/minimum-wages/annualised-salaries https://www.fairwork.gov.au/tools-and-resources/fact-sheets/rights-and-obligations/record-keeping-pay-slips | O6: Pay and employment rights | P6: 3 | Q6: Yes | R6: Question retained; answer guidance and risk/action pathways developed in v3.
A7: PAY02 | B7: PAY | C7: Pay & Entitlements | D7: How do you check that employees receive the pay and entitlements required for the work they actually perform? | E7: ALL | F7: 3 | G7: Yes | H7: Single choice: 0-3 / DK | I7: Include current rates, ordinary hours, overtime, penalties, breaks and pay frequency where relevant. Outsourced payroll can satisfy this control when the business checks its outputs. | J7: Q04;Q05;Q24;Q47 | K7: A_PAY02 | L7: PAY_ASSURANCE | M7: S06;S07;S14 | N7: https://www.fairwork.gov.au/pay-and-wages/minimum-wages/annualised-salaries https://www.fairwork.gov.au/newsroom/news/offsetting-and-record-keeping-salaried-employees https://www.fairwork.gov.au/tools-and-resources/fact-sheets/rights-and-obligations/record-keeping-pay-slips | O7: Pay and employment rights | P7: 3 | Q7: Yes | R7: Question retained; answer guidance and risk/action pathways developed in v3.
A8: PAY03 | B8: PAY | C8: Pay & Entitlements | D8: How are leave entitlements and payments checked when employment patterns or circumstances change? | E8: ALL | F8: 3 | G8: No | H8: Single choice: 0-3 / DK | I8: Include annual, personal/carer's, parental, compassionate and long service leave, public holidays and relevant loading. Different entitlements have different eligibility and payment rules. | J8: Q02;Q28;Q29;Q37;Q58 | K8: A_PAY03 | L8: LEAVE | M8: S14;S21;S28;S31;S39 | N8: https://www.fairwork.gov.au/tools-and-resources/fact-sheets/rights-and-obligations/record-keeping-pay-slips https://www.fairwork.gov.au/tools-and-resources/fact-sheets/minimum-workplace-entitlements/family-and-domestic-violence-leave https://www.fairwork.gov.au/leave/annual-leave/cashing-out-annual-leave https://www.nsw.gov.au/employment/rights-responsibilities/portable-long-service/csi-long-service-leave-scheme/employer-obligations https://www.fairwork.gov.au/employment-conditions/national-employment-standards | O8: Pay and employment rights | P8: 3 | Q8: No | R8: Question retained; answer guidance and risk/action pathways developed in v3.
A9: PAY04 | B9: PAY | C9: Pay & Entitlements | D9: How do you confirm that required superannuation contributions are calculated correctly and reach employees' funds on time? | E9: ALL | F9: 3 | G9: Yes | H9: Single choice: 0-3 / DK | I9: For earnings paid from 1 July 2026, Payday Super generally requires receipt by the fund, with allocation information, within seven business days after payday; some exceptions apply. Trace receipt rather than submission. Earlier earnings use the applicable earlier rules. | J9: NEW | K9: A_PAY04 | L9: SUPER | M9: S05;S24 | N9: https://www.ato.gov.au/businesses-and-organisations/super-for-employers/paying-super-on-payday/payment-deadlines-for-payday-super https://www.ato.gov.au/businesses-and-organisations/super-for-employers/work-out-if-you-have-to-pay-super/super-for-independent-contractors | O9: Superannuation and financial exposure | P9: 3 | Q9: Yes | R9: B19 legal-test wording clarified; PAY04 timing clarified; response outcomes developed in v3.
A10: PAY05 | B10: PAY | C10: Pay & Entitlements | D10: How do you check the timing and accuracy of employee payslips? | E10: ALL | F10: 2 | G10: No | H10: Single choice: 0-3 / DK | I10: Check required information for the actual pay arrangement, not whether every payslip uses the same layout. Payslips must generally be provided within one working day of payday. | J10: Q22;Q23 | K10: A_PAY05 | L10: PAY_ASSURANCE | M10: S14 | N10: https://www.fairwork.gov.au/tools-and-resources/fact-sheets/rights-and-obligations/record-keeping-pay-slips | O10: Employment records and transparency | P10: 2 | Q10: No | R10: Question retained; answer guidance and risk/action pathways developed in v3.
A11: PAY06 | B11: PAY | C11: Pay & Entitlements | D11: Could your business process paid family and domestic violence leave without exposing the employee's circumstances? | E11: ALL | F11: 3 | G11: Yes | H11: Single choice: 0-3 / DK | I11: Consider the entitlement, payment, evidence handling and payslip description. Assess the process, not whether anyone has disclosed an experience of violence. | J11: Q57 | K11: A_PAY06 | L11: SENSITIVE_LEAVE | M11: S21;S14 | N11: https://www.fairwork.gov.au/tools-and-resources/fact-sheets/minimum-workplace-entitlements/family-and-domestic-violence-leave https://www.fairwork.gov.au/tools-and-resources/fact-sheets/rights-and-obligations/record-keeping-pay-slips | O11: Personal safety and confidential information | P11: 3 | Q11: Yes | R11: Question retained; answer guidance and risk/action pathways developed in v3.
A12: CON01 | B12: CON | C12: Employment Contracts | D12: How reliably do your written employment terms reflect each person's current arrangement? | E12: ALL | F12: 2 | G12: No | H12: Single choice: 0-3 / DK | I12: Look for clear pay, employment type, hours and relevant terms. A longer contract or restrictive clause is not automatically a better contract. | J12: Q13;Q14 | K12: A_CON01 | L12: TERMS | M12: S06;S09 | N12: https://www.fairwork.gov.au/pay-and-wages/minimum-wages/annualised-salaries https://www.fairwork.gov.au/starting-employment/types-of-employees/fixed-term-contract-employees | O12: Employment clarity and disputes | P12: 2 | Q12: No | R12: Question retained; answer guidance and risk/action pathways developed in v3.
A13: CON02 | B13: CON | C13: Employment Contracts | D13: How do you check that each person's employment type reflects the arrangement in practice? | E13: ALL | F13: 3 | G13: No | H13: Single choice: 0-3 / DK | I13: Consider permanent full-time, permanent part-time, casual and fixed-term employment. Use the relevant follow-up where an arrangement needs a more specific check. | J13: Q07 | K13: A_CON02 | L13: TERMS | M13: S03;S09;S23 | N13: https://www.fairwork.gov.au/starting-employment/types-of-employees/casual-employees/becoming-a-permanent-employee https://www.fairwork.gov.au/starting-employment/types-of-employees/fixed-term-contract-employees https://www.fairwork.gov.au/find-help-for/independent-contractors/whole-of-relationship-test | O13: Employment status and entitlements | P13: 3 | Q13: No | R13: Question retained; answer guidance and risk/action pathways developed in v3.
A14: CON03 | B14: CON | C14: Employment Contracts | D14: How are changes to employment terms authorised, communicated and recorded? | E14: ALL | F14: 2 | G14: No | H14: Single choice: 0-3 / DK | I14: Distinguish a contractual change from a routine operational instruction. Identify consent, consultation or instrument requirements before the change. | J14: Q31 | K14: A_CON03 | L14: TERMS | M14: S25;S14 | N14: https://www.fairwork.gov.au/tools-and-resources/best-practice-guides/consultation-and-cooperation-in-the-workplace https://www.fairwork.gov.au/tools-and-resources/fact-sheets/rights-and-obligations/record-keeping-pay-slips | O14: Change control and pay accuracy | P14: 2 | Q14: No | R14: Question retained; answer guidance and risk/action pathways developed in v3.
A15: REC01 | B15: REC | C15: Recruitment & Talent | D15: Before recruiting, how clearly do you define what the role needs to achieve? | E15: ALL | F15: 2 | G15: No | H15: Single choice: 0-3 / DK | I15: A short role brief can be sufficient. Assess clarity of outcomes, essential requirements and responsibilities, not a fixed number of duties. | J15: Q09;Q10 | K15: A_REC01 | L15: HIRING | M15: S01;S27 | N15: https://www.abs.gov.au/statistics/standards/abs-forms-design-standards/2023/general-forms-design-principles-question-structure https://www.fairwork.gov.au/sites/default/files/migration/711/managing-underperformance-best-practice-guide.pdf | O15: Hiring quality and role clarity | P15: 2 | Q15: No | R15: Question retained; answer guidance and risk/action pathways developed in v3.
A16: REC02 | B16: REC | C16: Recruitment & Talent | D16: How do you make recruitment decisions fair, consistent and explainable? | E16: ALL | F16: 2 | G16: No | H16: Single choice: 0-3 / DK | I16: Comparable criteria matter more than mechanically identical conversations. Allow appropriate adjustments and assess evidence relevant to the role. Do not collect sensitive information that is unnecessary for assessing the role requirements. | J16: Q11;Q12 | K16: A_REC02 | L16: HIRING | M16: S01;S15 | N16: https://www.abs.gov.au/statistics/standards/abs-forms-design-standards/2023/general-forms-design-principles-question-structure https://www.oaic.gov.au/privacy/privacy-guidance-for-organisations-and-government-agencies/organisations/employee-records-exemption | O16: Fair selection and explainable decisions | P16: 3 | Q16: No | R16: Question retained; answer guidance and risk/action pathways developed in v3.
A17: REC03 | B17: REC | C17: Recruitment & Talent | D17: How accurately does the recruitment experience describe the job someone is joining? | E17: ALL | F17: 1 | G17: No | H17: Single choice: 0-3 / DK | I17: Consider the advert, interview, offer and communication. Do not score the business on whether every unsuccessful applicant receives a phone call. | J17: Q10;Q12 | K17: A_REC03 | L17: HIRING | M17: S01 | N17: https://www.abs.gov.au/statistics/standards/abs-forms-design-standards/2023/general-forms-design-principles-question-structure | O17: Expectation management and retention | P17: 2 | Q17: No | R17: Question retained; answer guidance and risk/action pathways developed in v3.
... A33: LND02 | B33: LND | C33: Training & Development | D33: How do you check whether training improves performance in the job? | E33: ALL | F33: 2 | G33: No | H33: Single choice: 0-3 / DK | I33: Course attendance is an input. Look for safe application, demonstrated skill, better work or reduced reliance on others. | J33: Q59 | K33: A_LND02 | L33: CAPABILITY | M33: S27 | N33: https://www.fairwork.gov.au/sites/default/files/migration/711/managing-underperformance-best-practice-guide.pdf | O33: Return on development effort | P33: 2 | Q33: No | R33: Question retained; answer guidance and risk/action pathways developed in v3.
A34: LND03 | B34: LND | C34: Training & Development | D34: What would happen to critical work if a key person were unexpectedly unavailable? | E34: ALL | F34: 2 | G34: No | H34: Single choice: 0-3 / DK | I34: Consider payroll, client delivery, approvals and specialist knowledge. This does not require a formal succession programme. | J34: Q59 | K34: A_LND03 | L34: CAPABILITY | M34: DESIGN | O34: Business continuity | P34: 3 | Q34: No | R34: Question retained; answer guidance and risk/action pathways developed in v3.
A35: CUL01 | B35: CUL | C35: Culture & Engagement | D35: How do you learn what employees experience at work and show what happens to their feedback? | E35: ALL | F35: 2 | G35: No | H35: Single choice: 0-3 / DK | I35: Use a method suitable for your size. A manager's positive view of the culture is not a substitute for employee input; a five-person survey is not necessarily anonymous. | J35: Q50 | K35: A_CUL01 | L35: CULTURE | M35: S25;S10 | N35: https://www.fairwork.gov.au/tools-and-resources/best-practice-guides/consultation-and-cooperation-in-the-workplace https://humanrights.gov.au/resource-hub/resources-for-organisations-businesses/positive-duty-pdfs/guidelines-for-complying-with-the-positive-duty-under-the-sex-discrimination-act-1984-cth | O35: Employee voice and follow-through | P35: 2 | Q35: No | R35: Question retained; answer guidance and risk/action pathways developed in v3.
A36: CUL02 | B36: CUL | C36: Culture & Engagement | D36: How do you understand and respond to the risk of losing employees you would prefer to retain? | E36: ALL | F36: 2 | G36: No | H36: Single choice: 0-3 / DK | I36: For a small team, consider individual retention concerns and departures rather than volatile percentages. If nobody has left recently, assess the way you identify and respond to retention concerns. | J36: Q48;Q47 | K36: A_CUL02 | L36: CULTURE | M36: DESIGN | O36: Retention and service continuity | P36: 2 | Q36: No | R36: Question retained; answer guidance and risk/action pathways developed in v3.
A37: CUL03 | B37: CUL | C37: Culture & Engagement | D37: How do employees see that contribution and opportunity are recognised fairly? | E37: ALL | F37: 1 | G37: No | H37: Single choice: 0-3 / DK | I37: Recognition need not involve spending money or organising events. Consider everyday feedback, allocation of opportunities and treatment of different work patterns. | J37: Q49;Q50 | K37: A_CUL03 | L37: CULTURE | M37: S10;S11 | N37: https://humanrights.gov.au/resource-hub/resources-for-organisations-businesses/positive-duty-pdfs/guidelines-for-complying-with-the-positive-duty-under-the-sex-discrimination-act-1984-cth https://www.safeworkaustralia.gov.au/safety-topic/managing-health-and-safety/mental-health/managing-risks/identifying-assessing-controlling-and-reviewing | O37: Fair opportunity and recognition | P37: 1 | Q37: No | R37: Question retained; answer guidance and risk/action pathways developed in v3.
A38: CUL04 | B38: CUL | C38: Culture & Engagement | D38: How do you hold people leaders accountable for the way they manage others? | E38: ALL | F38: 2 | G38: No | H38: Single choice: 0-3 / DK | I38: The owner is a people leader too. In an owner-managed business, employee feedback and periodic review of actual decisions can provide accountability; a formal management appraisal is not required. | J38: NEW | K38: A_CUL04 | L38: LEADERSHIP | M38: S10;S27 | N38: https://humanrights.gov.au/resource-hub/resources-for-organisations-businesses/positive-duty-pdfs/guidelines-for-complying-with-the-positive-duty-under-the-sex-discrimination-act-1984-cth https://www.fairwork.gov.au/sites/default/files/migration/711/managing-underperformance-best-practice-guide.pdf | O38: Leadership accountability | P38: 2 | Q38: No | R38: Question retained; answer guidance and risk/action pathways developed in v3.
A39: DAT01 | B39: DAT | C39: Record Keeping | D39: Could you reconstruct an employee's pay and entitlements from the records you keep? | E39: ALL | F39: 3 | G39: Yes | H39: Single choice: 0-3 / DK | I39: Include actual work and overtime where required, leave, changes, deductions and relevant approvals. A roster is not proof that actual hours matched it. Statutory record requirements vary by arrangement. | J39: Q21;Q27;Q37 | K39: A_DAT01 | L39: PAY_ASSURANCE | M39: S14;S07 | N39: https://www.fairwork.gov.au/tools-and-resources/fact-sheets/rights-and-obligations/record-keeping-pay-slips https://www.fairwork.gov.au/newsroom/news/offsetting-and-record-keeping-salaried-employees | O39: Pay records and evidentiary reliability | P39: 3 | Q39: Yes | R39: Question retained; answer guidance and risk/action pathways developed in v3.
A40: DAT02 | B40: DAT | C40: Record Keeping | D40: How do you protect employee and applicant information from unnecessary access or use? | E40: ALL | F40: 3 | G40: No | H40: Single choice: 0-3 / DK | I40: Consider collection, access, sharing, retention and deletion, including external providers. Privacy Act coverage and the employee-records exemption require separate assessment. | J40: Q27;Q12 | K40: A_DAT02 | L40: INFORMATION | M40: S15;S16;S17 | N40: https://www.oaic.gov.au/privacy/privacy-guidance-for-organisations-and-government-agencies/organisations/employee-records-exemption https://www.oaic.gov.au/privacy/privacy-guidance-for-organisations-and-government-agencies/organisations/small-business https://www.oaic.gov.au/news/media-centre/new-resources-on-transparency-for-use-of-ai-and-automated-decision-making | O40: Privacy and confidential information | P40: 3 | Q40: Yes | R40: Question retained; answer guidance and risk/action pathways developed in v3.
A41: DAT03 | B41: DAT | C41: Record Keeping | D41: Could the business retrieve essential people records if its usual administrator or system were unavailable? | E41: ALL | F41: 2 | G41: No | H41: Single choice: 0-3 / DK | I41: Consider authorised backup access, export capability, version control and a tested recovery method. Do not share personal passwords. | J41: Q27 | K41: A_DAT03 | L41: INFORMATION | M41: S14;S15 | N41: https://www.fairwork.gov.au/tools-and-resources/fact-sheets/rights-and-obligations/record-keeping-pay-slips https://www.oaic.gov.au/privacy/privacy-guidance-for-organisations-and-government-agencies/organisations/employee-records-exemption | O41: Record availability and continuity | P41: 3 | Q41: No | R41: Question retained; answer guidance and risk/action pathways developed in v3.
A42: EXT01 | B42: EXT | C42: Employee Exits | D42: Before ending employment, how do you check the reason, required process and protections that may apply? | E42: ALL | F42: 3 | G42: Yes | H42: Single choice: 0-3 / DK | I42: Include employees in probation and small businesses. Knowing how to defend a claim is not the same as making a sound decision before one arises. | J42: Q38;Q40;Q46;Q52;Q63;Q64 | K42: A_EXT01 | L42: FAIR_DECISIONS | M42: S02;S26 | N42: https://www.fairwork.gov.au/taxonomy/term/527 https://www.fairwork.gov.au/tools-and-resources/fact-sheets/minimum-workplace-entitlements/ending-employment | O42: Employment-ending decisions | P42: 3 | Q42: Yes | R42: Question retained; answer guidance and risk/action pathways developed in v3.
A43: EXT02 | B43: EXT | C43: Employee Exits | D43: How do you check final pay and employment documentation when a person leaves? | E43: ALL | F43: 3 | G43: No | H43: Single choice: 0-3 / DK | I43: Check the applicable notice, leave, redundancy where relevant, payment timing and permitted deductions. Different exit reasons can produce different entitlements. | J43: Q46 | K43: A_EXT02 | L43: EXIT | M43: S26;S08;S14 | N43: https://www.fairwork.gov.au/tools-and-resources/fact-sheets/minimum-workplace-entitlements/ending-employment https://www.fairwork.gov.au/pay-and-wages/deductions-and-related-issues/deducting-pay https://www.fairwork.gov.au/tools-and-resources/fact-sheets/rights-and-obligations/record-keeping-pay-slips | O43: Final pay and entitlements | P43: 3 | Q43: No | R43: Question retained; answer guidance and risk/action pathways developed in v3.
A44: EXT03 | B44: EXT | C44: Employee Exits | D44: How do you protect continuity and information when an employee leaves? | E44: ALL | F44: 2 | G44: No | H44: Single choice: 0-3 / DK | I44: Consider the timing of access changes, return of property, transfer of work and preservation of relevant records. Do not make payment conditional on property return without checking the law. | J44: NEW | K44: A_EXT03 | L44: EXIT | M44: S14;S15;S08 | N44: https://www.fairwork.gov.au/tools-and-resources/fact-sheets/rights-and-obligations/record-keeping-pay-slips https://www.oaic.gov.au/privacy/privacy-guidance-for-organisations-and-government-agencies/organisations/employee-records-exemption https://www.fairwork.gov.au/pay-and-wages/deductions-and-related-issues/deducting-pay | O44: Access, records and continuity | P44: 3 | Q44: No | R44: Question retained; answer guidance and risk/action pathways developed in v3.
A45: PSY01 | B45: PSY | C45: Psychosocial Risk & Positive Duty | D45: How do you identify aspects of work that could harm people's psychological health? | E45: ALL | F45: 3 | G45: Yes | H45: Single choice: 0-3 / DK | I45: Consider workload, role clarity, support, change, isolation, aggression and other work-related hazards. Seek input from workers rather than waiting for a formal complaint. | J45: Q50;Q60;Q62 | K45: A_PSY01 | L45: PSYCHOSOCIAL | M45: S11;S12 | N45: https://www.safeworkaustralia.gov.au/safety-topic/managing-health-and-safety/mental-health/managing-risks/identifying-assessing-controlling-and-reviewing https://www.safeworkaustralia.gov.au/safety-topic/managing-health-and-safety/mental-health/managing-risks/differences-between-whs-and-wellbeing | O45: Work-related psychological harm | P45: 3 | Q45: Yes | R45: Question retained; answer guidance and risk/action pathways developed in v3.
A46: PSY02 | B46: PSY | C46: Psychosocial Risk & Positive Duty | D46: What arrangements control the psychosocial risks arising from your work? | E46: ALL | F46: 3 | G46: Yes | H46: Single choice: 0-3 / DK | I46: Look for controls addressing workload, staffing, role design, supervision or aggression. Controls may already be built into how work is organised. Support services do not replace prevention; a new programme is not automatically required. | J46: Q60;Q62 | K46: A_PSY02 | L46: PSYCHOSOCIAL | M46: S11;S12 | N46: https://www.safeworkaustralia.gov.au/safety-topic/managing-health-and-safety/mental-health/managing-risks/identifying-assessing-controlling-and-reviewing https://www.safeworkaustralia.gov.au/safety-topic/managing-health-and-safety/mental-health/managing-risks/differences-between-whs-and-wellbeing | O46: Work-related psychological harm | P46: 3 | Q46: Yes | R46: Question retained; answer guidance and risk/action pathways developed in v3.
A47: PSY03 | B47: PSY | C47: Psychosocial Risk & Positive Duty | D47: How does your business actively prevent sexual harassment, sex-based harassment and related unlawful conduct? | E47: ALL | F47: 3 | G47: Yes | H47: Single choice: 0-3 / DK | I47: Consider the positive duty under the Sex Discrimination Act, including sex discrimination, hostile environments on the ground of sex and related victimisation. This duty is related to, but distinct from, general WHS duties. | J47: Q56 | K47: A_PSY03 | L47: RESPECT | M47: S10 | N47: https://humanrights.gov.au/resource-hub/resources-for-organisations-businesses/positive-duty-pdfs/guidelines-for-complying-with-the-positive-duty-under-the-sex-discrimination-act-1984-cth | O47: Prevention of unlawful workplace conduct | P47: 3 | Q47: Yes | R47: Question retained; answer guidance and risk/action pathways developed in v3.
A48: PSY04 | B48: PSY | C48: Psychosocial Risk & Positive Duty | D48: Could someone raise a concern safely if it involved their manager, the owner or a high-performing colleague? | E48: ALL | F48: 3 | G48: Yes | H48: Single choice: 0-3 / DK | I48: A reporting route must work when the usual contact is the subject of the concern. Do not promise anonymity where it cannot be delivered. | J48: Q56;Q50 | K48: A_PSY04 | L48: RESPECT | M48: S10;S11 | N48: https://humanrights.gov.au/resource-hub/resources-for-organisations-businesses/positive-duty-pdfs/guidelines-for-complying-with-the-positive-duty-under-the-sex-discrimination-act-1984-cth https://www.safeworkaustralia.gov.au/safety-topic/managing-health-and-safety/mental-health/managing-risks/identifying-assessing-controlling-and-reviewing | O48: Safe reporting and protection from retaliation | P48: 3 | Q48: Yes | R48: Question retained; answer guidance and risk/action pathways developed in v3.
... A74: B25 | B74: WHS | C74: Workplace Health & Safety | D74: How do you coordinate safety responsibilities when people work through a labour-hire or other shared-work arrangement? | E74: SHARED_WORK | F74: 3 | G74: Yes | H74: Single choice: 0-3 / DK | I74: Use for labour-hire placements or other work involving overlapping duty holders. Record who performs each safety task, but do not assume duties can be contracted away. Confirm applicable state or territory requirements. | J74: NEW v3 | K74: A_B25 | L74: SHARED_SAFETY | M74: S42;S13;S38 | N74: https://www.safeworkaustralia.gov.au/safety-topic/managing-health-and-safety/labour-hire/whs-duties https://www.safeworkaustralia.gov.au/safety-topic/managing-health-and-safety/identify-assess-and-control-hazards/managing-risks https://www.safeworkaustralia.gov.au/workers-compensation | O74: Shared work health and safety duties | P74: 3 | Q74: Yes | R74: New conditional question in v3

Sheet Answers
A1: Answer choices | practical detail without longer questions
A2: Four specific maturity choices plus an explicit unknown. Optional answer help supports an honest choice; evidence is requested as a type or example, not uploaded into a general assessment.
A3: DREAMSTONEHR | PROPOSED V3.0 | 10 OCTOBER 2026
A5: Question ID | B5: Answer ID | C5: Response code | D5: Scoring points | E5: Customer-facing answer | F5: Meaning | G5: Result handling | H5: Eligibility rule | I5: Help choosing this answer | J5: Evidence the business should be able to locate | K5: Outcome key
A6: PAY01 | B6: PAY01_0 | C6: 0 | D6: 0 | E6: We have not checked which rules apply to our roles. | F6: Practice absent or not established as described | G6: Outcome PAY01_0 supplies provisional risk, priority, reasons and actions. Apply contextual escalation separately. | H6: Confirmed exclusion only; DK retains the eligible denominator. | I6: Choose this when the statement describes the current position. Reporting a gap helps prioritise support; it is not an admission that a legal breach has occurred. | J6: A dated coverage and classification record with reasons for every distinct role, appropriate review of uncertain classifications, and resulting payroll changes checked. An unresolved classification remains an open task. | K6: PAY01_0
A7: PAY01 | B7: PAY01_1 | C7: 1 | D7: 1 | E7: We rely on job titles, past practice or payroll defaults, without a recorded coverage check. | F7: Assumption-dependent or inconsistent practice | G7: Outcome PAY01_1 supplies provisional risk, priority, reasons and actions. Apply contextual escalation separately. | H7: Confirmed exclusion only; DK retains the eligible denominator. | I7: Choose this when the process depends on assumptions, personal knowledge or ad hoc handling rather than a dependable check. | J7: A dated coverage and classification record with reasons for every distinct role, appropriate review of uncertain classifications, and resulting payroll changes checked. An unresolved classification remains an open task. | K7: PAY01_1
A8: PAY01 | B8: PAY01_2 | C8: 2 | D8: 2 | E8: We have checked some roles, but changes or exceptions remain unresolved. | F8: Partly established; residual gap remains | G8: Outcome PAY01_2 supplies provisional risk, priority, reasons and actions. Apply contextual escalation separately. | H8: Confirmed exclusion only; DK retains the eligible denominator. | I8: Choose this when important parts exist but at least one part of the statement remains unresolved. The report should target that gap, not require a full rebuild. | J8: A dated coverage and classification record with reasons for every distinct role, appropriate review of uncertain classifications, and resulting payroll changes checked. An unresolved classification remains an open task. | K8: PAY01_2
A9: PAY01 | B9: PAY01_3 | C9: 3 | D9: 3 | E9: We have a current record for every role, including the basis for any award-free classification, and review it when duties change. | F9: Established practice reported, not independently verified | G9: Outcome PAY01_3 supplies provisional risk, priority, reasons and actions. Apply contextual escalation separately. | H9: Confirmed exclusion only; DK retains the eligible denominator. | I9: Choose this only when the whole statement describes routine practice and you can point to a recent example or a tested readiness process. One successful exception is not enough. | J9: A dated coverage and classification record with reasons for every distinct role, appropriate review of uncertain classifications, and resulting payroll changes checked. An unresolved classification remains an open task. | K9: PAY01_3
A10: PAY01 | B10: PAY01_DK | C10: DK | D10: 0 | E10: I need to confirm this. | F10: Unverified, not an established failure | G10: Outcome PAY01_DK supplies provisional risk, priority, reasons and actions. Apply contextual escalation separately. | H10: Confirmed exclusion only; DK retains the eligible denominator. | I10: Choose this rather than guessing when you cannot confirm the practice or its consistency. You can save the assessment and ask the responsible person. | J10: A dated coverage and classification record with reasons for every distinct role, appropriate review of uncertain classifications, and resulting payroll changes checked. An unresolved classification remains an open task. | K10: PAY01_DK
A11: PAY02 | B11: PAY02_0 | C11: 0 | D11: 0 | E11: We have not checked payroll against actual work and applicable rules. | F11: Practice absent or not established as described | G11: Outcome PAY02_0 supplies provisional risk, priority, reasons and actions. Apply contextual escalation separately. | H11: Confirmed exclusion only; DK retains the eligible denominator. | I11: Choose this when the statement describes the current position. Reporting a gap helps prioritise support; it is not an admission that a legal breach has occurred. | J11: A dated pay-check record for each materially different pay arrangement, with discrepancies investigated, required corrections completed and the next affected pay run checked. Keep any unresolved scope or payment issue open. | K11: PAY02_0
A12: PAY02 | B12: PAY02_1 | C12: 1 | D12: 1 | E12: We assume our software, payroll provider or above-award rates make the payments correct. | F12: Assumption-dependent or inconsistent practice | G12: Outcome PAY02_1 supplies provisional risk, priority, reasons and actions. Apply contextual escalation separately. | H12: Confirmed exclusion only; DK retains the eligible denominator. | I12: Choose this when the process depends on assumptions, personal knowledge or ad hoc handling rather than a dependable check. | J12: A dated pay-check record for each materially different pay arrangement, with discrepancies investigated, required corrections completed and the next affected pay run checked. Keep any unresolved scope or payment issue open. | K12: PAY02_1
A13: PAY02 | B13: PAY02_2 | C13: 2 | D13: 2 | E13: We check base rates, but some working patterns or other entitlements have not been tested. | F13: Partly established; residual gap remains | G13: Outcome PAY02_2 supplies provisional risk, priority, reasons and actions. Apply contextual escalation separately. | H13: Confirmed exclusion only; DK retains the eligible denominator. | I13: Choose this when important parts exist but at least one part of the statement remains unresolved. The report should target that gap, not require a full rebuild. | J13: A dated pay-check record for each materially different pay arrangement, with discrepancies investigated, required corrections completed and the next affected pay run checked. Keep any unresolved scope or payment issue open. | K13: PAY02_2
A14: PAY02 | B14: PAY02_3 | C14: 3 | D14: 3 | E14: We check representative actual pay periods against applicable rules, document exceptions and verify that corrections are completed. | F14: Established practice reported, not independently verified | G14: Outcome PAY02_3 supplies provisional risk, priority, reasons and actions. Apply contextual escalation separately. | H14: Confirmed exclusion only; DK retains the eligible denominator. | I14: Choose this only when the whole statement describes routine practice and you can point to a recent example or a tested readiness process. One successful exception is not enough. | J14: A dated pay-check record for each materially different pay arrangement, with discrepancies investigated, required corrections completed and the next affected pay run checked. Keep any unresolved scope or payment issue open. | K14: PAY02_3
A15: PAY02 | B15: PAY02_DK | C15: DK | D15: 0 | E15: I need to confirm this. | F15: Unverified, not an established failure | G15: Outcome PAY02_DK supplies provisional risk, priority, reasons and actions. Apply contextual escalation separately. | H15: Confirmed exclusion only; DK retains the eligible denominator. | I15: Choose this rather than guessing when you cannot confirm the practice or its consistency. You can save the assessment and ask the responsible person. | J15: A dated pay-check record for each materially different pay arrangement, with discrepancies investigated, required corrections completed and the next affected pay run checked. Keep any unresolved scope or payment issue open. | K15: PAY02_DK
A16: PAY03 | B16: PAY03_0 | C16: 0 | D16: 0 | E16: Leave is handled without a consistent check of eligibility, balances or pay. | F16: Practice absent or not established as described | G16: Outcome PAY03_0 supplies provisional risk, priority, reasons and actions. Apply contextual escalation separately. | H16: Confirmed exclusion only; DK retains the eligible denominator. | I16: Choose this when the statement describes the current position. Reporting a gap helps prioritise support; it is not an admission that a legal breach has occurred. | J16: A dated leave reconciliation against the applicable rules, with incorrect balances or payments corrected and a follow-up transaction checked. State-based and instrument-specific matters are resolved or remain clearly open. | K16: PAY03_0
A17: PAY03 | B17: PAY03_1 | C17: 1 | D17: 1 | E17: We use the default payroll settings and deal with exceptions as they arise. | F17: Assumption-dependent or inconsistent practice | G17: Outcome PAY03_1 supplies provisional risk, priority, reasons and actions. Apply contextual escalation separately. | H17: Confirmed exclusion only; DK retains the eligible denominator. | I17: Choose this when the process depends on assumptions, personal knowledge or ad hoc handling rather than a dependable check. | J17: A dated leave reconciliation against the applicable rules, with incorrect balances or payments corrected and a follow-up transaction checked. State-based and instrument-specific matters are resolved or remain clearly open. | K17: PAY03_1
A18: PAY03 | B18: PAY03_2 | C18: 2 | D18: 2 | E18: Most leave is checked, but some employment types, jurisdictions or changes need review. | F18: Partly established; residual gap remains | G18: Outcome PAY03_2 supplies provisional risk, priority, reasons and actions. Apply contextual escalation separately. | H18: Confirmed exclusion only; DK retains the eligible denominator. | I18: Choose this when important parts exist but at least one part of the statement remains unresolved. The report should target that gap, not require a full rebuild. | J18: A dated leave reconciliation against the applicable rules, with incorrect balances or payments corrected and a follow-up transaction checked. State-based and instrument-specific matters are resolved or remain clearly open. | K18: PAY03_2
A19: PAY03 | B19: PAY03_3 | C19: 3 | D19: 3 | E19: We check the applicable entitlement and payment, maintain accurate balances and review settings when hours, service or rules change. | F19: Established practice reported, not independently verified | G19: Outcome PAY03_3 supplies provisional risk, priority, reasons and actions. Apply contextual escalation separately. | H19: Confirmed exclusion only; DK retains the eligible denominator. | I19: Choose this only when the whole statement describes routine practice and you can point to a recent example or a tested readiness process. One successful exception is not enough. | J19: A dated leave reconciliation against the applicable rules, with incorrect balances or payments corrected and a follow-up transaction checked. State-based and instrument-specific matters are resolved or remain clearly open. | K19: PAY03_3
A20: PAY03 | B20: PAY03_DK | C20: DK | D20: 0 | E20: I need to confirm this. | F20: Unverified, not an established failure | G20: Outcome PAY03_DK supplies provisional risk, priority, reasons and actions. Apply contextual escalation separately. | H20: Confirmed exclusion only; DK retains the eligible denominator. | I20: Choose this rather than guessing when you cannot confirm the practice or its consistency. You can save the assessment and ask the responsible person. | J20: A dated leave reconciliation against the applicable rules, with incorrect balances or payments corrected and a follow-up transaction checked. State-based and instrument-specific matters are resolved or remain clearly open. | K20: PAY03_DK
A21: PAY04 | B21: PAY04_0 | C21: 0 | D21: 0 | E21: We are not consistently paying required superannuation by the applicable deadline. | F21: Practice absent or not established as described | G21: Outcome PAY04_0 supplies provisional risk, priority, reasons and actions. Apply contextual escalation separately. | H21: Confirmed exclusion only; DK retains the eligible denominator. | I21: Choose this when the statement describes the current position. Reporting a gap helps prioritise support; it is not an admission that a legal breach has occurred. | J21: A contribution reconciliation showing actual fund receipt and any missed deadline, with shortfalls, rejected payments and related obligations addressed. A subsequent cycle demonstrates timely receipt; later correction does not erase an earlier delay. | K21: PAY04_0
A22: PAY04 | B22: PAY04_1 | C22: 1 | D22: 1 | E22: We rely on payroll or clearing-house submissions without checking rejected or late contributions. | F22: Assumption-dependent or inconsistent practice | G22: Outcome PAY04_1 supplies provisional risk, priority, reasons and actions. Apply contextual escalation separately. | H22: Confirmed exclusion only; DK retains the eligible denominator. | I22: Choose this when the process depends on assumptions, personal knowledge or ad hoc handling rather than a dependable check. | J22: A contribution reconciliation showing actual fund receipt and any missed deadline, with shortfalls, rejected payments and related obligations addressed. A subsequent cycle demonstrates timely receipt; later correction does not erase an earlier delay. | K22: PAY04_1
A23: PAY04 | B23: PAY04_2 | C23: 2 | D23: 2 | E23: We check payments, but some earnings, fund exceptions or receipt dates are unresolved. | F23: Partly established; residual gap remains | G23: Outcome PAY04_2 supplies provisional risk, priority, reasons and actions. Apply contextual escalation separately. | H23: Confirmed exclusion only; DK retains the eligible denominator. | I23: Choose this when important parts exist but at least one part of the statement remains unresolved. The report should target that gap, not require a full rebuild. | J23: A contribution reconciliation showing actual fund receipt and any missed deadline, with shortfalls, rejected payments and related obligations addressed. A subsequent cycle demonstrates timely receipt; later correction does not erase an earlier delay. | K23: PAY04_2
A24: PAY04 | B24: PAY04_3 | C24: 3 | D24: 3 | E24: We reconcile the applicable earnings, rate and fund receipt, and promptly resolve rejected or late contributions. | F24: Established practice reported, not independently verified | G24: Outcome PAY04_3 supplies provisional risk, priority, reasons and actions. Apply contextual escalation separately. | H24: Confirmed exclusion only; DK retains the eligible denominator. | I24: Choose this only when the whole statement describes routine practice and you can point to a recent example or a tested readiness process. One successful exception is not enough. | J24: A contribution reconciliation showing actual fund receipt and any missed deadline, with shortfalls, rejected payments and related obligations addressed. A subsequent cycle demonstrates timely receipt; later correction does not erase an earlier delay. | K24: PAY04_3
A25: PAY04 | B25: PAY04_DK | C25: DK | D25: 0 | E25: I need to confirm this. | F25: Unverified, not an established failure | G25: Outcome PAY04_DK supplies provisional risk, priority, reasons and actions. Apply contextual escalation separately. | H25: Confirmed exclusion only; DK retains the eligible denominator. | I25: Choose this rather than guessing when you cannot confirm the practice or its consistency. You can save the assessment and ask the responsible person. | J25: A contribution reconciliation showing actual fund receipt and any missed deadline, with shortfalls, rejected payments and related obligations addressed. A subsequent cycle demonstrates timely receipt; later correction does not erase an earlier delay. | K25: PAY04_DK
A26: PAY05 | B26: PAY05_0 | C26: 0 | D26: 0 | E26: Payslips are not consistently provided. | F26: Practice absent or not established as described | G26: Outcome PAY05_0 supplies provisional risk, priority, reasons and actions. Apply contextual escalation separately. | H26: Confirmed exclusion only; DK retains the eligible denominator. | I26: Choose this when the statement describes the current position. Reporting a gap helps prioritise support; it is not an admission that a legal breach has occurred. | J26: A completed payslip check, required corrections issued, delivery/access confirmed and a subsequent payslip checked. Preserve the original record and how any past failure was addressed. | K26: PAY05_0
A27: PAY05 | B27: PAY05_1 | C27: 1 | D27: 1 | E27: Payslips are produced, but timing or required fields have not been checked. | F27: Assumption-dependent or inconsistent practice | G27: Outcome PAY05_1 supplies provisional risk, priority, reasons and actions. Apply contextual escalation separately. | H27: Confirmed exclusion only; DK retains the eligible denominator. | I27: Choose this when the process depends on assumptions, personal knowledge or ad hoc handling rather than a dependable check. | J27: A completed payslip check, required corrections issued, delivery/access confirmed and a subsequent payslip checked. Preserve the original record and how any past failure was addressed. | K27: PAY05_1
A28: PAY05 | B28: PAY05_2 | C28: 2 | D28: 2 | E28: Timing and most details are correct, but some arrangements or exceptions need checking. | F28: Partly established; residual gap remains | G28: Outcome PAY05_2 supplies provisional risk, priority, reasons and actions. Apply contextual escalation separately. | H28: Confirmed exclusion only; DK retains the eligible denominator. | I28: Choose this when important parts exist but at least one part of the statement remains unresolved. The report should target that gap, not require a full rebuild. | J28: A completed payslip check, required corrections issued, delivery/access confirmed and a subsequent payslip checked. Preserve the original record and how any past failure was addressed. | K28: PAY05_2
A29: PAY05 | B29: PAY05_3 | C29: 3 | D29: 3 | E29: We have checked timing, required fields and secure employee access across our pay arrangements. | F29: Established practice reported, not independently verified | G29: Outcome PAY05_3 supplies provisional risk, priority, reasons and actions. Apply contextual escalation separately. | H29: Confirmed exclusion only; DK retains the eligible denominator. | I29: Choose this only when the whole statement describes routine practice and you can point to a recent example or a tested readiness process. One successful exception is not enough. | J29: A completed payslip check, required corrections issued, delivery/access confirmed and a subsequent payslip checked. Preserve the original record and how any past failure was addressed. | K29: PAY05_3
A30: PAY05 | B30: PAY05_DK | C30: DK | D30: 0 | E30: I need to confirm this. | F30: Unverified, not an established failure | G30: Outcome PAY05_DK supplies provisional risk, priority, reasons and actions. Apply contextual escalation separately. | H30: Confirmed exclusion only; DK retains the eligible denominator. | I30: Choose this rather than guessing when you cannot confirm the practice or its consistency. You can save the assessment and ask the responsible person. | J30: A completed payslip check, required corrections issued, delivery/access confirmed and a subsequent payslip checked. Preserve the original record and how any past failure was addressed. | K30: PAY05_DK
A31: PAY06 | B31: PAY06_0 | C31: 0 | D31: 0 | E31: We do not have a process for this leave. | F31: Practice absent or not established as described | G31: Outcome PAY06_0 supplies provisional risk, priority, reasons and actions. Apply contextual escalation separately. | H31: Confirmed exclusion only; DK retains the eligible denominator. | I31: Choose this when the statement describes the current position. Reporting a gap helps prioritise support; it is not an admission that a legal breach has occurred. | J31: A tested confidential workflow and fictional payslip, with a named contact for employees. | K31: PAY06_0
A32: PAY06 | B32: PAY06_1 | C32: 1 | D32: 1 | E32: We would work it out when requested, including how to protect the information. | F32: Assumption-dependent or inconsistent practice | G32: Outcome PAY06_1 supplies provisional risk, priority, reasons and actions. Apply contextual escalation separately. | H32: Confirmed exclusion only; DK retains the eligible denominator. | I32: Choose this when the process depends on assumptions, personal knowledge or ad hoc handling rather than a dependable check. | J32: A tested confidential workflow and fictional payslip, with a named contact for employees. | K32: PAY06_1
A33: PAY06 | B33: PAY06_2 | C33: 2 | D33: 2 | E33: We have guidance, but payroll treatment or confidentiality has not been checked. | F33: Partly established; residual gap remains | G33: Outcome PAY06_2 supplies provisional risk, priority, reasons and actions. Apply contextual escalation separately. | H33: Confirmed exclusion only; DK retains the eligible denominator. | I33: Choose this when important parts exist but at least one part of the statement remains unresolved. The report should target that gap, not require a full rebuild. | J33: A tested confidential workflow and fictional payslip, with a named contact for employees. | K33: PAY06_2
A34: PAY06 | B34: PAY06_3 | C34: 3 | D34: 3 | E34: Authorised staff can apply the entitlement and payment rules, protect supporting information and use an appropriate payslip description. | F34: Established practice reported, not independently verified | G34: Outcome PAY06_3 supplies provisional risk, priority, reasons and actions. Apply contextual escalation separately. | H34: Confirmed exclusion only; DK retains the eligible denominator. | I34: Choose this only when the whole statement describes routine practice and you can point to a recent example or a tested readiness process. One successful exception is not enough. | J34: A tested confidential workflow and fictional payslip, with a named contact for employees. | K34: PAY06_3
A35: PAY06 | B35: PAY06_DK | C35: DK | D35: 0 | E35: I need to confirm this. | F35: Unverified, not an established failure | G35: Outcome PAY06_DK supplies provisional risk, priority, reasons and actions. Apply contextual escalation separately. | H35: Confirmed exclusion only; DK retains the eligible denominator. | I35: Choose this rather than guessing when you cannot confirm the practice or its consistency. You can save the assessment and ask the responsible person. | J35: A tested confidential workflow and fictional payslip, with a named contact for employees. | K35: PAY06_DK
A36: CON01 | B36: CON01_0 | C36: 0 | D36: 0 | E36: Some or all employees have no clear written terms. | F36: Practice absent or not established as described | G36: Outcome CON01_0 supplies provisional risk, priority, reasons and actions. Apply contextual escalation separately. | H36: Confirmed exclusion only; DK retains the eligible denominator. | I36: Choose this when the statement describes the current position. Reporting a gap helps prioritise support; it is not an admission that a legal breach has occurred. | J36: Current employment terms match the actual arrangements, required agreement and communication are recorded, and material exceptions have been resolved. A register tracks the next review; merely listing missing contracts does not close the task. | K36: CON01_0
A37: CON01 | B37: CON01_1 | C37: 1 | D37: 1 | E37: We use a template, but it has not been checked for the role or current arrangement. | F37: Assumption-dependent or inconsistent practice | G37: Outcome CON01_1 supplies provisional risk, priority, reasons and actions. Apply contextual escalation separately. | H37: Confirmed exclusion only; DK retains the eligible denominator. | I37: Choose this when the process depends on assumptions, personal knowledge or ad hoc handling rather than a dependable check. | J37: Current employment terms match the actual arrangements, required agreement and communication are recorded, and material exceptions have been resolved. A register tracks the next review; merely listing missing contracts does not close the task. | K37: CON01_1
A38: CON01 | B38: CON01_2 | C38: 2 | D38: 2 | E38: Most terms are current, but some employees have unsigned, inconsistent or outdated documents. | F38: Partly established; residual gap remains | G38: Outcome CON01_2 supplies provisional risk, priority, reasons and actions. Apply contextual escalation separately. | H38: Confirmed exclusion only; DK retains the eligible denominator. | I38: Choose this when important parts exist but at least one part of the statement remains unresolved. The report should target that gap, not require a full rebuild. | J38: Current employment terms match the actual arrangements, required agreement and communication are recorded, and material exceptions have been resolved. A register tracks the next review; merely listing missing contracts does not close the task. | K38: CON01_2
A39: CON01 | B39: CON01_3 | C39: 3 | D39: 3 | E39: We hold clear, current terms for each employee and can demonstrate that relevant terms were communicated and agreed. | F39: Established practice reported, not independently verified | G39: Outcome CON01_3 supplies provisional risk, priority, reasons and actions. Apply contextual escalation separately. | H39: Confirmed exclusion only; DK retains the eligible denominator. | I39: Choose this only when the whole statement describes routine practice and you can point to a recent example or a tested readiness process. One successful exception is not enough. | J39: Current employment terms match the actual arrangements, required agreement and communication are recorded, and material exceptions have been resolved. A register tracks the next review; merely listing missing contracts does not close the task. | K39: CON01_3
A40: CON01 | B40: CON01_DK | C40: DK | D40: 0 | E40: I need to confirm this. | F40: Unverified, not an established failure | G40: Outcome CON01_DK supplies provisional risk, priority, reasons and actions. Apply contextual escalation separately. | H40: Confirmed exclusion only; DK retains the eligible denominator. | I40: Choose this rather than guessing when you cannot confirm the practice or its consistency. You can save the assessment and ask the responsible person. | J40: Current employment terms match the actual arrangements, required agreement and communication are recorded, and material exceptions have been resolved. A register tracks the next review; merely listing missing contracts does not close the task. | K40: CON01_DK
A41: CON02 | B41: CON02_0 | C41: 0 | D41: 0 | E41: Employment types have not been reviewed. | F41: Practice absent or not established as described | G41: Outcome CON02_0 supplies provisional risk, priority, reasons and actions. Apply contextual escalation separately. | H41: Confirmed exclusion only; DK retains the eligible denominator. | I41: Choose this when the statement describes the current position. Reporting a gap helps prioritise support; it is not an admission that a legal breach has occurred. | J41: Each materially different employment arrangement has a recorded assessment and any necessary changes have been agreed, implemented and checked. Keep unresolved status or entitlement questions open. | K41: CON02_0
A42: CON02 | B42: CON02_1 | C42: 1 | D42: 1 | E42: We retain the original label even when the working arrangement changes. | F42: Assumption-dependent or inconsistent practice | G42: Outcome CON02_1 supplies provisional risk, priority, reasons and actions. Apply contextual escalation separately. | H42: Confirmed exclusion only; DK retains the eligible denominator. | I42: Choose this when the process depends on assumptions, personal knowledge or ad hoc handling rather than a dependable check. | J42: Each materially different employment arrangement has a recorded assessment and any necessary changes have been agreed, implemented and checked. Keep unresolved status or entitlement questions open. | K42: CON02_1
A43: CON02 | B43: CON02_2 | C43: 2 | D43: 2 | E43: Most arrangements have been reviewed, but some changes or exceptions remain unresolved. | F43: Partly established; residual gap remains | G43: Outcome CON02_2 supplies provisional risk, priority, reasons and actions. Apply contextual escalation separately. | H43: Confirmed exclusion only; DK retains the eligible denominator. | I43: Choose this when important parts exist but at least one part of the statement remains unresolved. The report should target that gap, not require a full rebuild. | J43: Each materially different employment arrangement has a recorded assessment and any necessary changes have been agreed, implemented and checked. Keep unresolved status or entitlement questions open. | K43: CON02_2
A44: CON02 | B44: CON02_3 | C44: 3 | D44: 3 | E44: We check the basis for engagement and revisit it when the pattern of work or contractual arrangement changes. | F44: Established practice reported, not independently verified | G44: Outcome CON02_3 supplies provisional risk, priority, reasons and actions. Apply contextual escalation separately. | H44: Confirmed exclusion only; DK retains the eligible denominator. | I44: Choose this only when the whole statement describes routine practice and you can point to a recent example or a tested readiness process. One successful exception is not enough. | J44: Each materially different employment arrangement has a recorded assessment and any necessary changes have been agreed, implemented and checked. Keep unresolved status or entitlement questions open. | K44: CON02_3
A45: CON02 | B45: CON02_DK | C45: DK | D45: 0 | E45: I need to confirm this. | F45: Unverified, not an established failure | G45: Outcome CON02_DK supplies provisional risk, priority, reasons and actions. Apply contextual escalation separately. | H45: Confirmed exclusion only; DK retains the eligible denominator. | I45: Choose this rather than guessing when you cannot confirm the practice or its consistency. You can save the assessment and ask the responsible person. | J45: Each materially different employment arrangement has a recorded assessment and any necessary changes have been agreed, implemented and checked. Keep unresolved status or entitlement questions open. | K45: CON02_DK
A46: CON03 | B46: CON03_0 | C46: 0 | D46: 0 | E46: Changes are made without a consistent process. | F46: Practice absent or not established as described | G46: Outcome CON03_0 supplies provisional risk, priority, reasons and actions. Apply contextual escalation separately. | H46: Confirmed exclusion only; DK retains the eligible denominator. | I46: Choose this when the statement describes the current position. Reporting a gap helps prioritise support; it is not an admission that a legal breach has occurred. | J46: A complete change record with approvals, required agreement or consultation and matching payroll instructions. | K46: CON03_0
A47: CON03 | B47: CON03_1 | C47: 1 | D47: 1 | E47: Managers generally agree changes verbally or by informal messages. | F47: Assumption-dependent or inconsistent practice | G47: Outcome CON03_1 supplies provisional risk, priority, reasons and actions. Apply contextual escalation separately. | H47: Confirmed exclusion only; DK retains the eligible denominator. | I47: Choose this when the process depends on assumptions, personal knowledge or ad hoc handling rather than a dependable check. | J47: A complete change record with approvals, required agreement or consultation and matching payroll instructions. | K47: CON03_1
A48: CON03 | B48: CON03_2 | C48: 2 | D48: 2 | E48: Most changes are recorded, but agreement, payroll updates or filing can be missed. | F48: Partly established; residual gap remains | G48: Outcome CON03_2 supplies provisional risk, priority, reasons and actions. Apply contextual escalation separately. | H48: Confirmed exclusion only; DK retains the eligible denominator. | I48: Choose this when important parts exist but at least one part of the statement remains unresolved. The report should target that gap, not require a full rebuild. | J48: A complete change record with approvals, required agreement or consultation and matching payroll instructions. | K48: CON03_2
A49: CON03 | B49: CON03_3 | C49: 3 | D49: 3 | E49: We check the authority and required process, record relevant agreement and ensure payroll and employee records match the change. | F49: Established practice reported, not independently verified | G49: Outcome CON03_3 supplies provisional risk, priority, reasons and actions. Apply contextual escalation separately. | H49: Confirmed exclusion only; DK retains the eligible denominator. | I49: Choose this only when the whole statement describes routine practice and you can point to a recent example or a tested readiness process. One successful exception is not enough. | J49: A complete change record with approvals, required agreement or consultation and matching payroll instructions. | K49: CON03_3
A50: CON03 | B50: CON03_DK | C50: DK | D50: 0 | E50: I need to confirm this. | F50: Unverified, not an established failure | G50: Outcome CON03_DK supplies provisional risk, priority, reasons and actions. Apply contextual escalation separately. | H50: Confirmed exclusion only; DK retains the eligible denominator. | I50: Choose this rather than guessing when you cannot confirm the practice or its consistency. You can save the assessment and ask the responsible person. | J50: A complete change record with approvals, required agreement or consultation and matching payroll instructions. | K50: CON03_DK
A51: REC01 | B51: REC01_0 | C51: 0 | D51: 0 | E51: We usually start recruiting without a clear role brief. | F51: Practice absent or not established as described | G51: Outcome REC01_0 supplies provisional risk, priority, reasons and actions. Apply contextual escalation separately. | H51: Confirmed exclusion only; DK retains the eligible denominator. | I51: Choose this when the statement describes the current position. Reporting a gap helps prioritise support; it is not an admission that a legal breach has occurred. | J51: An agreed role brief that the advert, selection criteria and initial performance goals reflect. | K51: REC01_0
A52: REC01 | B52: REC01_1 | C52: 1 | D52: 1 | E52: We reuse an old description or describe the previous employee's work. | F52: Assumption-dependent or inconsistent practice | G52: Outcome REC01_1 supplies provisional risk, priority, reasons and actions. Apply contextual escalation separately. | H52: Confirmed exclusion only; DK retains the eligible denominator. | I52: Choose this when the process depends on assumptions, personal knowledge or ad hoc handling rather than a dependable check. | J52: An agreed role brief that the advert, selection criteria and initial performance goals reflect. | K52: REC01_1
A53: REC01 | B53: REC01_2 | C53: 2 | D53: 2 | E53: We set out key duties, but outcomes, essential requirements or role boundaries are unclear. | F53: Partly established; residual gap remains | G53: Outcome REC01_2 supplies provisional risk, priority, reasons and actions. Apply contextual escalation separately. | H53: Confirmed exclusion only; DK retains the eligible denominator. | I53: Choose this when important parts exist but at least one part of the statement remains unresolved. The report should target that gap, not require a full rebuild. | J53: An agreed role brief that the advert, selection criteria and initial performance goals reflect. | K53: REC01_2
A54: REC01 | B54: REC01_3 | C54: 3 | D54: 3 | E54: We confirm the business need, expected outcomes and genuine role requirements, and use that brief consistently in recruitment. | F54: Established practice reported, not independently verified | G54: Outcome REC01_3 supplies provisional risk, priority, reasons and actions. Apply contextual escalation separately. | H54: Confirmed exclusion only; DK retains the eligible denominator. | I54: Choose this only when the whole statement describes routine practice and you can point to a recent example or a tested readiness process. One successful exception is not enough. | J54: An agreed role brief that the advert, selection criteria and initial performance goals reflect. | K54: REC01_3
A55: REC01 | B55: REC01_DK | C55: DK | D55: 0 | E55: I need to confirm this. | F55: Unverified, not an established failure | G55: Outcome REC01_DK supplies provisional risk, priority, reasons and actions. Apply contextual escalation separately. | H55: Confirmed exclusion only; DK retains the eligible denominator. | I55: Choose this rather than guessing when you cannot confirm the practice or its consistency. You can save the assessment and ask the responsible person. | J55: An agreed role brief that the advert, selection criteria and initial performance goals reflect. | K55: REC01_DK
A56: REC02 | B56: REC02_0 | C56: 0 | D56: 0 | E56: Hiring decisions mainly rely on personal impressions. | F56: Practice absent or not established as described | G56: Outcome REC02_0 supplies provisional risk, priority, reasons and actions. Apply contextual escalation separately. | H56: Confirmed exclusion only; DK retains the eligible denominator. | I56: Choose this when the statement describes the current position. Reporting a gap helps prioritise support; it is not an admission that a legal breach has occurred. | J56: A completed selection record and an appropriate applicant-information handling process. | K56: REC02_0
A57: REC02 | B57: REC02_1 | C57: 1 | D57: 1 | E57: We use some common questions, but do not consistently record the basis for decisions. | F57: Assumption-dependent or inconsistent practice | G57: Outcome REC02_1 supplies provisional risk, priority, reasons and actions. Apply contextual escalation separately. | H57: Confirmed exclusion only; DK retains the eligible denominator. | I57: Choose this when the process depends on assumptions, personal knowledge or ad hoc handling rather than a dependable check. | J57: A completed selection record and an appropriate applicant-information handling process. | K57: REC02_1
A58: REC02 | B58: REC02_2 | C58: 2 | D58: 2 | E58: We assess role-related criteria, but scoring, adjustments or records vary between interviewers. | F58: Partly established; residual gap remains | G58: Outcome REC02_2 supplies provisional risk, priority, reasons and actions. Apply contextual escalation separately. | H58: Confirmed exclusion only; DK retains the eligible denominator. | I58: Choose this when important parts exist but at least one part of the statement remains unresolved. The report should target that gap, not require a full rebuild. | J58: A completed selection record and an appropriate applicant-information handling process. | K58: REC02_2
A59: REC02 | B59: REC02_3 | C59: 3 | D59: 3 | E59: We use role-related criteria, consider appropriate adjustments and record evidence supporting the decision, while protecting applicant information. | F59: Established practice reported, not independently verified | G59: Outcome REC02_3 supplies provisional risk, priority, reasons and actions. Apply contextual escalation separately. | H59: Confirmed exclusion only; DK retains the eligible denominator. | I59: Choose this only when the whole statement describes routine practice and you can point to a recent example or a tested readiness process. One successful exception is not enough. | J59: A completed selection record and an appropriate applicant-information handling process. | K59: REC02_3
A60: REC02 | B60: REC02_DK | C60: DK | D60: 0 | E60: I need to confirm this. | F60: Unverified, not an established failure | G60: Outcome REC02_DK supplies provisional risk, priority, reasons and actions. Apply contextual escalation separately. | H60: Confirmed exclusion only; DK retains the eligible denominator. | I60: Choose this rather than guessing when you cannot confirm the practice or its consistency. You can save the assessment and ask the responsible person. | J60: A completed selection record and an appropriate applicant-information handling process. | K60: REC02_DK
A61: REC03 | B61: REC03_0 | C61: 0 | D61: 0 | E61: The role or offer can differ substantially from what candidates were told. | F61: Practice absent or not established as described | G61: Outcome REC03_0 supplies provisional risk, priority, reasons and actions. Apply contextual escalation separately. | H61: Confirmed exclusion only; DK retains the eligible denominator. | I61: Choose this when the statement describes the current position. Reporting a gap helps prioritise support; it is not an admission that a legal breach has occurred. | J61: Consistent candidate information and a simple communication checklist. | K61: REC03_0
A62: REC03 | B62: REC03_1 | C62: 1 | D62: 1 | E62: Communication depends on the individual manager and there is no clear follow-through. | F62: Assumption-dependent or inconsistent practice | G62: Outcome REC03_1 supplies provisional risk, priority, reasons and actions. Apply contextual escalation separately. | H62: Confirmed exclusion only; DK retains the eligible denominator. | I62: Choose this when the process depends on assumptions, personal knowledge or ad hoc handling rather than a dependable check. | J62: Consistent candidate information and a simple communication checklist. | K62: REC03_1
A63: REC03 | B63: REC03_2 | C63: 2 | D63: 2 | E63: Candidates receive useful information, but some expectations or decisions are not clearly communicated. | F63: Partly established; residual gap remains | G63: Outcome REC03_2 supplies provisional risk, priority, reasons and actions. Apply contextual escalation separately. | H63: Confirmed exclusion only; DK retains the eligible denominator. | I63: Choose this when important parts exist but at least one part of the statement remains unresolved. The report should target that gap, not require a full rebuild. | J63: Consistent candidate information and a simple communication checklist. | K63: REC03_2
A64: REC03 | B64: REC03_3 | C64: 3 | D64: 3 | E64: Candidates receive a realistic account of the work and terms, timely communication and an opportunity to ask informed questions. | F64: Established practice reported, not independently verified | G64: Outcome REC03_3 supplies provisional risk, priority, reasons and actions. Apply contextual escalation separately. | H64: Confirmed exclusion only; DK retains the eligible denominator. | I64: Choose this only when the whole statement describes routine practice and you can point to a recent example or a tested readiness process. One successful exception is not enough. | J64: Consistent candidate information and a simple communication checklist. | K64: REC03_3
A65: REC03 | B65: REC03_DK | C65: DK | D65: 0 | E65: I need to confirm this. | F65: Unverified, not an established failure | G65: Outcome REC03_DK supplies provisional risk, priority, reasons and actions. Apply contextual escalation separately. | H65: Confirmed exclusion only; DK retains the eligible denominator. | I65: Choose this rather than guessing when you cannot confirm the practice or its consistency. You can save the assessment and ask the responsible person. | J65: Consistent candidate information and a simple communication checklist. | K65: REC03_DK
A66: ONB01 | B66: ONB01_0 | C66: 0 | D66: 0 | E66: We do not verify work rights. | F66: Practice absent or not established as described | G66: Outcome ONB01_0 supplies provisional risk, priority, reasons and actions. Apply contextual escalation separately. | H66: Confirmed exclusion only; DK retains the eligible denominator. | I66: Choose this when the statement describes the current position. Reporting a gap helps prioritise support; it is not an admission that a legal breach has occurred. | J66: A secure verification record and reminders for any restrictions or expiry dates that need action. | K66: ONB01_0
A67: ONB01 | B67: ONB01_1 | C67: 1 | D67: 1 | E67: We rely on what the applicant tells us or on assumptions about citizenship. | F67: Assumption-dependent or inconsistent practice | G67: Outcome ONB01_1 supplies provisional risk, priority, reasons and actions. Apply contextual escalation separately. | H67: Confirmed exclusion only; DK retains the eligible denominator. | I67: Choose this when the process depends on assumptions, personal knowledge or ad hoc handling rather than a dependable check. | J67: A secure verification record and reminders for any restrictions or expiry dates that need action. | K67: ONB01_1
A68: ONB01 | B68: ONB01_2 | C68: 2 | D68: 2 | E68: We collect evidence, but restrictions or expiry dates are not consistently tracked. | F68: Partly established; residual gap remains | G68: Outcome ONB01_2 supplies provisional risk, priority, reasons and actions. Apply contextual escalation separately. | H68: Confirmed exclusion only; DK retains the eligible denominator. | I68: Choose this when important parts exist but at least one part of the statement remains unresolved. The report should target that gap, not require a full rebuild. | J68: A secure verification record and reminders for any restrictions or expiry dates that need action. | K68: ONB01_2
A69: ONB01 | B69: ONB01_3 | C69: 3 | D69: 3 | E69: We verify appropriate evidence before work starts and monitor relevant restrictions and expiry dates. | F69: Established practice reported, not independently verified | G69: Outcome ONB01_3 supplies provisional risk, priority, reasons and actions. Apply contextual escalation separately. | H69: Confirmed exclusion only; DK retains the eligible denominator. | I69: Choose this only when the whole statement describes routine practice and you can point to a recent example or a tested readiness process. One successful exception is not enough. | J69: A secure verification record and reminders for any restrictions or expiry dates that need action. | K69: ONB01_3
A70: ONB01 | B70: ONB01_DK | C70: DK | D70: 0 | E70: I need to confirm this. | F70: Unverified, not an established failure | G70: Outcome ONB01_DK supplies provisional risk, priority, reasons and actions. Apply contextual escalation separately. | H70: Confirmed exclusion only; DK retains the eligible denominator. | I70: Choose this rather than guessing when you cannot confirm the practice or its consistency. You can save the assessment and ask the responsible person. | J70: A secure verification record and reminders for any restrictions or expiry dates that need action. | K70: ONB01_DK
A71: ONB02 | B71: ONB02_0 | C71: 0 | D71: 0 | E71: Statements are not provided consistently. | F71: Practice absent or not established as described | G71: Outcome ONB02_0 supplies provisional risk, priority, reasons and actions. Apply contextual escalation separately. | H71: Confirmed exclusion only; DK retains the eligible denominator. | I71: Choose this when the statement describes the current position. Reporting a gap helps prioritise support; it is not an admission that a legal breach has occurred. | J71: An onboarding delivery record, with additional reminders where the employment type requires them. | K71: ONB02_0
A72: ONB02 | B72: ONB02_1 | C72: 1 | D72: 1 | E72: We assume they are included in onboarding but do not check delivery. | F72: Assumption-dependent or inconsistent practice | G72: Outcome ONB02_1 supplies provisional risk, priority, reasons and actions. Apply contextual escalation separately. | H72: Confirmed exclusion only; DK retains the eligible denominator. | I72: Choose this when the process depends on assumptions, personal knowledge or ad hoc handling rather than a dependable check. | J72: An onboarding delivery record, with additional reminders where the employment type requires them. | K72: ONB02_1
A73: ONB02 | B73: ONB02_2 | C73: 2 | D73: 2 | E73: They are usually provided, but version control or delivery records are incomplete. | F73: Partly established; residual gap remains | G73: Outcome ONB02_2 supplies provisional risk, priority, reasons and actions. Apply contextual escalation separately. | H73: Confirmed exclusion only; DK retains the eligible denominator. | I73: Choose this when important parts exist but at least one part of the statement remains unresolved. The report should target that gap, not require a full rebuild. | J73: An onboarding delivery record, with additional reminders where the employment type requires them. | K73: ONB02_2
A74: ONB02 | B74: ONB02_3 | C74: 3 | D74: 3 | E74: We provide the current required statements at the relevant time and retain a record of delivery. | F74: Established practice reported, not independently verified | G74: Outcome ONB02_3 supplies provisional risk, priority, reasons and actions. Apply contextual escalation separately. | H74: Confirmed exclusion only; DK retains the eligible denominator. | I74: Choose this only when the whole statement describes routine practice and you can point to a recent example or a tested readiness process. One successful exception is not enough. | J74: An onboarding delivery record, with additional reminders where the employment type requires them. | K74: ONB02_3
A75: ONB02 | B75: ONB02_DK | C75: DK | D75: 0 | E75: I need to confirm this. | F75: Unverified, not an established failure | G75: Outcome ONB02_DK supplies provisional risk, priority, reasons and actions. Apply contextual escalation separately. | H75: Confirmed exclusion only; DK retains the eligible denominator. | I75: Choose this rather than guessing when you cannot confirm the practice or its consistency. You can save the assessment and ask the responsible person. | J75: An onboarding delivery record, with additional reminders where the employment type requires them. | K75: ONB02_DK
A76: ONB03 | B76: ONB03_0 | C76: 0 | D76: 0 | E76: New starters are largely expected to work things out themselves. | F76: Practice absent or not established as described | G76: Outcome ONB03_0 supplies provisional risk, priority, reasons and actions. Apply contextual escalation separately. | H76: Confirmed exclusion only; DK retains the eligible denominator. | I76: Choose this when the statement describes the current position. Reporting a gap helps prioritise support; it is not an admission that a legal breach has occurred. | J76: The new starter has completed the role-relevant induction, demonstrated the required understanding or capability and received follow-up support. Unresolved safety or capability restrictions remain active until addressed. | K76: ONB03_0
A77: ONB03 | B77: ONB03_1 | C77: 1 | D77: 1 | E77: We cover practical basics, but training and follow-up depend on who is available. | F77: Assumption-dependent or inconsistent practice | G77: Outcome ONB03_1 supplies provisional risk, priority, reasons and actions. Apply contextual escalation separately. | H77: Confirmed exclusion only; DK retains the eligible denominator. | I77: Choose this when the process depends on assumptions, personal knowledge or ad hoc handling rather than a dependable check. | J77: The new starter has completed the role-relevant induction, demonstrated the required understanding or capability and received follow-up support. Unresolved safety or capability restrictions remain active until addressed. | K77: ONB03_1
A78: ONB03 | B78: ONB03_2 | C78: 2 | D78: 2 | E78: We use an induction plan, but understanding or follow-up is not consistently checked. | F78: Partly established; residual gap remains | G78: Outcome ONB03_2 supplies provisional risk, priority, reasons and actions. Apply contextual escalation separately. | H78: Confirmed exclusion only; DK retains the eligible denominator. | I78: Choose this when important parts exist but at least one part of the statement remains unresolved. The report should target that gap, not require a full rebuild. | J78: The new starter has completed the role-relevant induction, demonstrated the required understanding or capability and received follow-up support. Unresolved safety or capability restrictions remain active until addressed. | K78: ONB03_2
A79: ONB03 | B79: ONB03_3 | C79: 3 | D79: 3 | E79: We provide a role-appropriate induction, check understanding and schedule early follow-up on capability and support. | F79: Established practice reported, not independently verified | G79: Outcome ONB03_3 supplies provisional risk, priority, reasons and actions. Apply contextual escalation separately. | H79: Confirmed exclusion only; DK retains the eligible denominator. | I79: Choose this only when the whole statement describes routine practice and you can point to a recent example or a tested readiness process. One successful exception is not enough. | J79: The new starter has completed the role-relevant induction, demonstrated the required understanding or capability and received follow-up support. Unresolved safety or capability restrictions remain active until addressed. | K79: ONB03_3
A80: ONB03 | B80: ONB03_DK | C80: DK | D80: 0 | E80: I need to confirm this. | F80: Unverified, not an established failure | G80: Outcome ONB03_DK supplies provisional risk, priority, reasons and actions. Apply contextual escalation separately. | H80: Confirmed exclusion only; DK retains the eligible denominator. | I80: Choose this rather than guessing when you cannot confirm the practice or its consistency. You can save the assessment and ask the responsible person. | J80: The new starter has completed the role-relevant induction, demonstrated the required understanding or capability and received follow-up support. Unresolved safety or capability restrictions remain active until addressed. | K80: ONB03_DK
A81: POL01 | B81: POL01_0 | C81: 0 | D81: 0 | E81: Key workplace expectations and processes are not clearly documented. | F81: Practice absent or not established as described | G81: Outcome POL01_0 supplies provisional risk, priority, reasons and actions. Apply contextual escalation separately. | H81: Confirmed exclusion only; DK retains the eligible denominator. | I81: Choose this when the statement describes the current position. Reporting a gap helps prioritise support; it is not an admission that a legal breach has occurred. | J81: A proportionate policy register with owners, current versions and accessible locations. | K81: POL01_0
A82: POL01 | B82: POL01_1 | C82: 1 | D82: 1 | E82: We use generic documents that have not been checked against our work. | F82: Assumption-dependent or inconsistent practice | G82: Outcome POL01_1 supplies provisional risk, priority, reasons and actions. Apply contextual escalation separately. | H82: Confirmed exclusion only; DK retains the eligible denominator. | I82: Choose this when the process depends on assumptions, personal knowledge or ad hoc handling rather than a dependable check. | J82: A proportionate policy register with owners, current versions and accessible locations. | K82: POL01_1
A83: POL01 | B83: POL01_2 | C83: 2 | D83: 2 | E83: We have relevant policies, but ownership, updates or accessibility are inconsistent. | F83: Partly established; residual gap remains | G83: Outcome POL01_2 supplies provisional risk, priority, reasons and actions. Apply contextual escalation separately. | H83: Confirmed exclusion only; DK retains the eligible denominator. | I83: Choose this when important parts exist but at least one part of the statement remains unresolved. The report should target that gap, not require a full rebuild. | J83: A proportionate policy register with owners, current versions and accessible locations. | K83: POL01_2
A84: POL01 | B84: POL01_3 | C84: 3 | D84: 3 | E84: Our policies address the business's actual requirements, are accessible and have a named owner and review process. | F84: Established practice reported, not independently verified | G84: Outcome POL01_3 supplies provisional risk, priority, reasons and actions. Apply contextual escalation separately. | H84: Confirmed exclusion only; DK retains the eligible denominator. | I84: Choose this only when the whole statement describes routine practice and you can point to a recent example or a tested readiness process. One successful exception is not enough. | J84: A proportionate policy register with owners, current versions and accessible locations. | K84: POL01_3
A85: POL01 | B85: POL01_DK | C85: DK | D85: 0 | E85: I need to confirm this. | F85: Unverified, not an established failure | G85: Outcome POL01_DK supplies provisional risk, priority, reasons and actions. Apply contextual escalation separately. | H85: Confirmed exclusion only; DK retains the eligible denominator. | I85: Choose this rather than guessing when you cannot confirm the practice or its consistency. You can save the assessment and ask the responsible person. | J85: A proportionate policy register with owners, current versions and accessible locations. | K85: POL01_DK
A86: POL02 | B86: POL02_0 | C86: 0 | D86: 0 | E86: Policies are rarely explained or consistently followed. | F86: Practice absent or not established as described | G86: Outcome POL02_0 supplies provisional risk, priority, reasons and actions. Apply contextual escalation separately. | H86: Confirmed exclusion only; DK retains the eligible denominator. | I86: Choose this when the statement describes the current position. Reporting a gap helps prioritise support; it is not an admission that a legal breach has occurred. | J86: A practical implementation check shows that staff and managers understand the relevant expectations, use the process and handle exceptions consistently. Required guidance or process changes have been implemented and checked. | K86: POL02_0
A87: POL02 | B87: POL02_1 | C87: 1 | D87: 1 | E87: We collect acknowledgements, but do not check understanding or application. | F87: Assumption-dependent or inconsistent practice | G87: Outcome POL02_1 supplies provisional risk, priority, reasons and actions. Apply contextual escalation separately. | H87: Confirmed exclusion only; DK retains the eligible denominator. | I87: Choose this when the process depends on assumptions, personal knowledge or ad hoc handling rather than a dependable check. | J87: A practical implementation check shows that staff and managers understand the relevant expectations, use the process and handle exceptions consistently. Required guidance or process changes have been implemented and checked. | K87: POL02_1
A88: POL02 | B88: POL02_2 | C88: 2 | D88: 2 | E88: Managers usually follow the policies, but exceptions or gaps are not consistently addressed. | F88: Partly established; residual gap remains | G88: Outcome POL02_2 supplies provisional risk, priority, reasons and actions. Apply contextual escalation separately. | H88: Confirmed exclusion only; DK retains the eligible denominator. | I88: Choose this when important parts exist but at least one part of the statement remains unresolved. The report should target that gap, not require a full rebuild. | J88: A practical implementation check shows that staff and managers understand the relevant expectations, use the process and handle exceptions consistently. Required guidance or process changes have been implemented and checked. | K88: POL02_2
A89: POL02 | B89: POL02_3 | C89: 3 | D89: 3 | E89: We explain the relevant expectations, check understanding and review how policies are applied across the business. | F89: Established practice reported, not independently verified | G89: Outcome POL02_3 supplies provisional risk, priority, reasons and actions. Apply contextual escalation separately. | H89: Confirmed exclusion only; DK retains the eligible denominator. | I89: Choose this only when the whole statement describes routine practice and you can point to a recent example or a tested readiness process. One successful exception is not enough. | J89: A practical implementation check shows that staff and managers understand the relevant expectations, use the process and handle exceptions consistently. Required guidance or process changes have been implemented and checked. | K89: POL02_3
A90: POL02 | B90: POL02_DK | C90: DK | D90: 0 | E90: I need to confirm this. | F90: Unverified, not an established failure | G90: Outcome POL02_DK supplies provisional risk, priority, reasons and actions. Apply contextual escalation separately. | H90: Confirmed exclusion only; DK retains the eligible denominator. | I90: Choose this rather than guessing when you cannot confirm the practice or its consistency. You can save the assessment and ask the responsible person. | J90: A practical implementation check shows that staff and managers understand the relevant expectations, use the process and handle exceptions consistently. Required guidance or process changes have been implemented and checked. | K90: POL02_DK
A91: POL03 | B91: POL03_0 | C91: 0 | D91: 0 | E91: We do not have a process for considering these requests. | F91: Practice absent or not established as described | G91: Outcome POL03_0 supplies provisional risk, priority, reasons and actions. Apply contextual escalation separately. | H91: Confirmed exclusion only; DK retains the eligible denominator. | I91: Choose this when the statement describes the current position. Reporting a gap helps prioritise support; it is not an admission that a legal breach has occurred. | J91: A tested request-handling process and, where a request exists, a documented decision and response meeting the applicable requirements. Agreed arrangements are implemented and reviewed; an unanswered request remains open. | K91: POL03_0
A92: POL03 | B92: POL03_1 | C92: 1 | D92: 1 | E92: We would apply a general policy or manager preference without considering the individual request. | F92: Assumption-dependent or inconsistent practice | G92: Outcome POL03_1 supplies provisional risk, priority, reasons and actions. Apply contextual escalation separately. | H92: Confirmed exclusion only; DK retains the eligible denominator. | I92: Choose this when the process depends on assumptions, personal knowledge or ad hoc handling rather than a dependable check. | J92: A tested request-handling process and, where a request exists, a documented decision and response meeting the applicable requirements. Agreed arrangements are implemented and reviewed; an unanswered request remains open. | K92: POL03_1
A93: POL03 | B93: POL03_2 | C93: 2 | D93: 2 | E93: We consider individual circumstances, but timing, discussion or written reasons are inconsistent. | F93: Partly established; residual gap remains | G93: Outcome POL03_2 supplies provisional risk, priority, reasons and actions. Apply contextual escalation separately. | H93: Confirmed exclusion only; DK retains the eligible denominator. | I93: Choose this when important parts exist but at least one part of the statement remains unresolved. The report should target that gap, not require a full rebuild. | J93: A tested request-handling process and, where a request exists, a documented decision and response meeting the applicable requirements. Agreed arrangements are implemented and reviewed; an unanswered request remains open. | K93: POL03_2
A94: POL03 | B94: POL03_3 | C94: 3 | D94: 3 | E94: We assess eligibility, discuss the request and alternatives, and provide a reasoned written response within the applicable timeframe. | F94: Established practice reported, not independently verified | G94: Outcome POL03_3 supplies provisional risk, priority, reasons and actions. Apply contextual escalation separately. | H94: Confirmed exclusion only; DK retains the eligible denominator. | I94: Choose this only when the whole statement describes routine practice and you can point to a recent example or a tested readiness process. One successful exception is not enough. | J94: A tested request-handling process and, where a request exists, a documented decision and response meeting the applicable requirements. Agreed arrangements are implemented and reviewed; an unanswered request remains open. | K94: POL03_3
A95: POL03 | B95: POL03_DK | C95: DK | D95: 0 | E95: I need to confirm this. | F95: Unverified, not an established failure | G95: Outcome POL03_DK supplies provisional risk, priority, reasons and actions. Apply contextual escalation separately. | H95: Confirmed exclusion only; DK retains the eligible denominator. | I95: Choose this rather than guessing when you cannot confirm the practice or its consistency. You can save the assessment and ask the responsible person. | J95: A tested request-handling process and, where a request exists, a documented decision and response meeting the applicable requirements. Agreed arrangements are implemented and reviewed; an unanswered request remains open. | K95: POL03_DK
A96: WHS01 | B96: WHS01_0 | C96: 0 | D96: 0 | E96: We have not systematically identified the hazards. | F96: Practice absent or not established as described | G96: Outcome WHS01_0 supplies provisional risk, priority, reasons and actions. Apply contextual escalation separately. | H96: Confirmed exclusion only; DK retains the eligible denominator. | I96: Choose this when the statement describes the current position. Reporting a gap helps prioritise support; it is not an admission that a legal breach has occurred. | J96: A task-relevant risk and control record with workers' input and completed follow-up. | K96: WHS01_0
A97: WHS01 | B97: WHS01_1 | C97: 1 | D97: 1 | E97: We mainly respond after an incident or rely on general safety reminders. | F97: Assumption-dependent or inconsistent practice | G97: Outcome WHS01_1 supplies provisional risk, priority, reasons and actions. Apply contextual escalation separately. | H97: Confirmed exclusion only; DK retains the eligible denominator. | I97: Choose this when the process depends on assumptions, personal knowledge or ad hoc handling rather than a dependable check. | J97: A task-relevant risk and control record with workers' input and completed follow-up. | K97: WHS01_1
A98: WHS01 | B98: WHS01_2 | C98: 2 | D98: 2 | E98: We have identified hazards and controls, but some tasks, workers or reviews are missing. | F98: Partly established; residual gap remains | G98: Outcome WHS01_2 supplies provisional risk, priority, reasons and actions. Apply contextual escalation separately. | H98: Confirmed exclusion only; DK retains the eligible denominator. | I98: Choose this when important parts exist but at least one part of the statement remains unresolved. The report should target that gap, not require a full rebuild. | J98: A task-relevant risk and control record with workers' input and completed follow-up. | K98: WHS01_2
A99: WHS01 | B99: WHS01_3 | C99: 3 | D99: 3 | E99: We consult workers, identify relevant hazards, implement suitable controls and check that they work. | F99: Established practice reported, not independently verified | G99: Outcome WHS01_3 supplies provisional risk, priority, reasons and actions. Apply contextual escalation separately. | H99: Confirmed exclusion only; DK retains the eligible denominator. | I99: Choose this only when the whole statement describes routine practice and you can point to a recent example or a tested readiness process. One successful exception is not enough. | J99: A task-relevant risk and control record with workers' input and completed follow-up. | K99: WHS01_3
A100: WHS01 | B100: WHS01_DK | C100: DK | D100: 0 | E100: I need to confirm this. | F100: Unverified, not an established failure | G100: Outcome WHS01_DK supplies provisional risk, priority, reasons and actions. Apply contextual escalation separately. | H100: Confirmed exclusion only; DK retains the eligible denominator. | I100: Choose this rather than guessing when you cannot confirm the practice or its consistency. You can save the assessment and ask the responsible person. | J100: A task-relevant risk and control record with workers' input and completed follow-up. | K100: WHS01_DK
A101: WHS02 | B101: WHS02_0 | C101: 0 | D101: 0 | E101: We do not have workable emergency arrangements. | F101: Practice absent or not established as described | G101: Outcome WHS02_0 supplies provisional risk, priority, reasons and actions. Apply contextual escalation separately. | H101: Confirmed exclusion only; DK retains the eligible denominator. | I101: Choose this when the statement describes the current position. Reporting a gap helps prioritise support; it is not an admission that a legal breach has occurred. | J101: A reviewed emergency plan and readiness check covering relevant people, shifts and locations. | K101: WHS02_0
...

Sheet Action Library
A1: Action library | complete practical work instructions
A2: 69 action cards. The primary legal guidance is linked; potential consequences, sequencing and priority choices are proposed DreamStoneHR product design. Tailor each card through Answer Outcomes.
A3: DREAMSTONEHR | PROPOSED V3.0 | 10 OCTOBER 2026
A5: Action ID | B5: Question ID | C5: Priority / trigger | D5: Finding headline | E5: Why it matters | F5: Practical first step | G5: Evidence of completion | H5: Suggested owner | I5: Suggested timing | J5: Small-business application | K5: Larger / more complex application | L5: Optional DreamStoneHR support | M5: Action family | N5: Source IDs | O5: Primary source URLs | P5: Consequence class | Q5: Step 2: establish or repair | R5: Step 3: test effectiveness | S5: Avoid this shortcut | T5: Recheck trigger | U5: Prerequisite question IDs
A6: A_PAY01 | B6: PAY01 | C6: Use PAY01_0 / _1 / _2 / _3 / _DK in Answer Outcomes, then apply Risk Context. Weight is not the risk rating. | D6: Establish the rules behind your pay decisions | E6: An incorrect coverage or classification decision can affect pay, leave and working conditions every time the role is paid. | F6: List each distinct role, actual duties, employment type, instrument and classification. Resolve uncertain roles before relying on the payroll settings. | G6: A dated coverage and classification record with reasons for every distinct role, appropriate review of uncertain classifications, and resulting payroll changes checked. An unresolved classification remains an open task. | H6: Payroll lead / owner | I6: Risk Method timing is the initial response target; actual duties and earlier events take precedence. Recheck: A changed role, new instrument or classification change. | J6: A dated role/pay register, a short sample check and an owner for exceptions can be sufficient evidence of the process. | K6: Sample different roles, instruments, pay patterns and locations. Record exception escalation and independent review responsibilities. | L6: Targeted payroll, award/classification or salary-arrangement review, scoped to the flagged population. | M6: PAY_ASSURANCE | N6: S06;S14 | O6: https://www.fairwork.gov.au/pay-and-wages/minimum-wages/annualised-salaries https://www.fairwork.gov.au/tools-and-resources/fact-sheets/rights-and-obligations/record-keeping-pay-slips | P6: 3 | Q6: Compare actual duties with the relevant coverage and classification provisions. Record the reasoning and refer unresolved cases for competent review. | R6: Check that the approved outcome matches payroll and contract records. Review comparable roles if one classification was wrong. | S6: A familiar job title, an ABN or an above-award salary is not evidence of correct coverage. | T6: A changed role, new instrument or classification change. | U6: None
A7: A_PAY02 | B7: PAY02 | C7: Use PAY02_0 / _1 / _2 / _3 / _DK in Answer Outcomes, then apply Risk Context. Weight is not the risk rating. | D7: Test the payroll result, not just the base rate | E7: An unchecked pay rule can repeat across pay periods and employees. The initial gap is lack of assurance, not proof of an underpayment. | F7: Select representative ordinary and exception pay periods and obtain the actual work records, applicable rules and payslips. Define the arrangements being checked before calculating any difference. | G7: A dated pay-check record for each materially different pay arrangement, with discrepancies investigated, required corrections completed and the next affected pay run checked. Keep any unresolved scope or payment issue open. | H7: Payroll lead / owner | I7: Risk Method timing is the initial response target; actual duties and earlier events take precedence. Recheck: A pay-rule change, payroll migration, discrepancy or new work pattern. | J7: A dated role/pay register, a short sample check and an owner for exceptions can be sufficient evidence of the process. | K7: Sample different roles, instruments, pay patterns and locations. Record exception escalation and independent review responsibilities. | L7: Targeted payroll, award/classification or salary-arrangement review, scoped to the flagged population. | M7: PAY_ASSURANCE | N7: S06;S07;S14 | O7: https://www.fairwork.gov.au/pay-and-wages/minimum-wages/annualised-salaries https://www.fairwork.gov.au/newsroom/news/offsetting-and-record-keeping-salaried-employees https://www.fairwork.gov.au/tools-and-resources/fact-sheets/rights-and-obligations/record-keeping-pay-slips | P7: 3 | Q7: Recalculate selected ordinary and exception pay periods using actual work records. Record differences by entitlement, period and affected arrangement. | R7: Investigate the cause of each difference, extend the review where appropriate and test the next affected pay run after correction. | S7: A clean payroll report only shows that the system processed its current settings. | T7: A pay-rule change, payroll migration, discrepancy or new work pattern. | U7: PAY01;DAT01
A8: A_PAY03 | B8: PAY03 | C8: Use PAY03_0 / _1 / _2 / _3 / _DK in Answer Outcomes, then apply Risk Context. Weight is not the risk rating. | D8: Check leave against the person and their circumstances | E8: Incorrect accruals or leave payments can deprive employees of entitlements and distort the business's leave liability. | F8: Reconcile a sample of leave balances and payments to ordinary hours, service and the applicable rules. Record which exceptions need specialist checking. | G8: A dated leave reconciliation against the applicable rules, with incorrect balances or payments corrected and a follow-up transaction checked. State-based and instrument-specific matters are resolved or remain clearly open. | H8: Payroll lead / owner | I8: Risk Method timing is the initial response target; actual duties and earlier events take precedence. Recheck: Changed hours, service milestones, an instrument change or a leave discrepancy. | J8: A dated role/pay register, a short sample check and an owner for exceptions can be sufficient evidence of the process. | K8: Sample different roles, instruments, pay patterns and locations. Record exception escalation and independent review responsibilities. | L8: Targeted payroll, award/classification or salary-arrangement review, scoped to the flagged population. | M8: LEAVE | N8: S14;S21;S28;S31;S39 | O8: https://www.fairwork.gov.au/tools-and-resources/fact-sheets/rights-and-obligations/record-keeping-pay-slips https://www.fairwork.gov.au/tools-and-resources/fact-sheets/minimum-workplace-entitlements/family-and-domestic-violence-leave https://www.fairwork.gov.au/leave/annual-leave/cashing-out-annual-leave https://www.nsw.gov.au/employment/rights-responsibilities/portable-long-service/csi-long-service-leave-scheme/employer-obligations https://www.fairwork.gov.au/employment-conditions/national-employment-standards | P8: 3 | Q8: Check accrual and payment rules for relevant employment types and changes in hours or service. Reconcile opening balances and adjustments. | R8: Resolve differences, retain the calculation trail and check a later leave transaction against the corrected rule. | S8: A balance that looks plausible is not the same as a reconciled balance. | T8: Changed hours, service milestones, an instrument change or a leave discrepancy. | U8: PAY01
A9: A_PAY04 | B9: PAY04 | C9: Use PAY04_0 / _1 / _2 / _3 / _DK in Answer Outcomes, then apply Risk Context. Weight is not the risk rating. | D9: Confirm super reaches the fund | E9: A contribution recorded as submitted may still be rejected or received late. Unresolved earnings or receipt exceptions need prompt checking. | F9: Trace the most recent pay cycle from earnings to fund receipt. Check rejected contributions and record the follow-up process and responsible person. | G9: A contribution reconciliation showing actual fund receipt and any missed deadline, with shortfalls, rejected payments and related obligations addressed. A subsequent cycle demonstrates timely receipt; later correction does not erase an earlier delay. | H9: Payroll lead / owner | I9: Risk Method timing is the initial response target; actual duties and earlier events take precedence. Recheck: Each pay cycle and any returned payment, changed fund or payroll change. | J9: A dated role/pay register, a short sample check and an owner for exceptions can be sufficient evidence of the process. | K9: Sample different roles, instruments, pay patterns and locations. Record exception escalation and independent review responsibilities. | L9: Targeted payroll, award/classification or salary-arrangement review, scoped to the flagged population. | M9: SUPER | N9: S05;S24 | O9: https://www.ato.gov.au/businesses-and-organisations/super-for-employers/paying-super-on-payday/payment-deadlines-for-payday-super https://www.ato.gov.au/businesses-and-organisations/super-for-employers/work-out-if-you-have-to-pay-super/super-for-independent-contractors | P9: 3 | Q9: Match the amount and employee details to the applicable earnings and contribution rules. Identify rejected, unallocated or late items. | R9: Resolve exceptions with payroll, the fund or the relevant adviser and retain receipt evidence. Check a subsequent payment cycle. | S9: Treating clearing-house submission as proof that the contribution reached the fund on time. | T9: Each pay cycle and any returned payment, changed fund or payroll change. | U9: PAY02
A10: A_PAY05 | B10: PAY05 | C10: Use PAY05_0 / _1 / _2 / _3 / _DK in Answer Outcomes, then apply Risk Context. Weight is not the risk rating. | D10: Check what employees actually receive | E10: Late or incomplete payslips make payments harder to understand and can leave mandatory information missing. | F10: Inspect a payslip for each materially different pay arrangement, check issue timing and confirm employees can access it privately. | G10: A completed payslip check, required corrections issued, delivery/access confirmed and a subsequent payslip checked. Preserve the original record and how any past failure was addressed. | H10: Payroll lead / owner | I10: Risk Method timing is the initial response target; actual duties and earlier events take precedence. Recheck: Changed payslip templates, payroll systems or pay arrangements. | J10: A dated role/pay register, a short sample check and an owner for exceptions can be sufficient evidence of the process. | K10: Sample different roles, instruments, pay patterns and locations. Record exception escalation and independent review responsibilities. | L10: Targeted payroll, award/classification or salary-arrangement review, scoped to the flagged population. | M10: PAY_ASSURANCE | N10: S14 | O10: https://www.fairwork.gov.au/tools-and-resources/fact-sheets/rights-and-obligations/record-keeping-pay-slips | P10: 2 | Q10: Compare issue timing and required fields against the actual payment arrangement. Correct template and delivery problems. | R10: Check the next payslip and confirm employees can access it privately, including people without routine system access. | S10: Checking one standard payslip while overlooking a different payment arrangement. | T10: Changed payslip templates, payroll systems or pay arrangements. | U10: PAY01
A11: A_PAY06 | B11: PAY06 | C11: Use PAY06_0 / _1 / _2 / _3 / _DK in Answer Outcomes, then apply Risk Context. Weight is not the risk rating. | D11: Make sensitive leave safe to access | E11: Poor leave administration can disclose sensitive circumstances or prevent access to an entitlement. The assessment must never ask for the employee's story. | F11: Run a fictional leave request through your approval and payroll process. Check authorised access, the payment calculation and what appears on the payslip. | G11: A tested confidential workflow and fictional payslip, with a named contact for employees. | H11: Payroll lead / owner | I11: Risk Method timing is the initial response target; actual duties and earlier events take precedence. Recheck: A change in payroll settings, leave administrators or confidentiality controls. | J11: A dated role/pay register, a short sample check and an owner for exceptions can be sufficient evidence of the process. | K11: Sample different roles, instruments, pay patterns and locations. Record exception escalation and independent review responsibilities. | L11: Targeted payroll, award/classification or salary-arrangement review, scoped to the flagged population. | M11: SENSITIVE_LEAVE | N11: S21;S14 | O11: https://www.fairwork.gov.au/tools-and-resources/fact-sheets/minimum-workplace-entitlements/family-and-domestic-violence-leave https://www.fairwork.gov.au/tools-and-resources/fact-sheets/rights-and-obligations/record-keeping-pay-slips | P11: 3 | Q11: Give authorised staff a discreet process covering entitlement checks, payment, evidence access and the payslip treatment. | R11: Run a fictional request through the process and inspect every point where the information could be exposed. | S11: Using a detailed leave label or circulating supporting material more widely than necessary. | T11: A change in payroll settings, leave administrators or confidentiality controls. | U11: DAT02
A12: A_CON01 | B12: CON01 | C12: Use CON01_0 / _1 / _2 / _3 / _DK in Answer Outcomes, then apply Risk Context. Weight is not the risk rating. | D12: Bring the written terms into line with the real job | E12: Outdated or unclear terms can create a mismatch between what was agreed, what employees expect and what payroll applies. | F12: Compare your employee list with the current contract and variation held for each person. Resolve missing or inconsistent terms through an appropriate review and agreement process. | G12: Current employment terms match the actual arrangements, required agreement and communication are recorded, and material exceptions have been resolved. A register tracks the next review; merely listing missing contracts does not close the task. | H12: Owner / HR lead | I12: Risk Method timing is the initial response target; actual duties and earlier events take precedence. Recheck: A material change in role, pay, hours or template requirements. | J12: A current terms register and a controlled set of suitable templates can be proportionate. | K12: Use controlled templates, approval limits and version/variation tracking across entities and roles. | L12: Employment terms and engagement review, with legal referral for issues outside the agreed HR advisory scope. | M12: TERMS | N12: S06;S09 | O12: https://www.fairwork.gov.au/pay-and-wages/minimum-wages/annualised-salaries https://www.fairwork.gov.au/starting-employment/types-of-employees/fixed-term-contract-employees | P12: 2 | Q12: Compare current work and pay with the recorded terms. Review the suitability of the template and any proposed changes before seeking agreement. | R12: Reconcile the final agreed terms to payroll and retain an accessible version history. | S12: Treating a signature or a long contract as proof that the terms are suitable or lawful. | T12: A material change in role, pay, hours or template requirements. | U12: PAY01
A13: A_CON02 | B13: CON02 | C13: Use CON02_0 / _1 / _2 / _3 / _DK in Answer Outcomes, then apply Risk Context. Weight is not the risk rating. | D13: Review employment labels against actual arrangements | E13: An employment label that no longer matches the arrangement can result in the wrong rights, payments or decision process being applied. | F13: Compare current work patterns with recorded employment types. Investigate exceptions rather than automatically relabelling employees. | G13: Each materially different employment arrangement has a recorded assessment and any necessary changes have been agreed, implemented and checked. Keep unresolved status or entitlement questions open. | H13: Owner / HR lead | I13: Risk Method timing is the initial response target; actual duties and earlier events take precedence. Recheck: A changed pattern of work, renewal or changed engagement rules. | J13: A current terms register and a controlled set of suitable templates can be proportionate. | K13: Use controlled templates, approval limits and version/variation tracking across entities and roles. | L13: Employment terms and engagement review, with legal referral for issues outside the agreed HR advisory scope. | M13: TERMS | N13: S03;S09;S23 | O13: https://www.fairwork.gov.au/starting-employment/types-of-employees/casual-employees/becoming-a-permanent-employee https://www.fairwork.gov.au/starting-employment/types-of-employees/fixed-term-contract-employees https://www.fairwork.gov.au/find-help-for/independent-contractors/whole-of-relationship-test | P13: 3 | Q13: Review the relevant engagement basis and working pattern. Use the casual, fixed-term or contractor branch where needed. | R13: Record the assessment and implement any required change through a checked process, rather than simply relabelling payroll. | S13: Keeping the original employment type indefinitely because the contract uses that label. | T13: A changed pattern of work, renewal or changed engagement rules. | U13: PAY01
A14: A_CON03 | B14: CON03 | C14: Use CON03_0 / _1 / _2 / _3 / _DK in Answer Outcomes, then apply Risk Context. Weight is not the risk rating. | D14: Close the gap between agreement and implementation | E14: An agreed change can fail in practice if payroll, management and the employee hold different versions of it. | F14: Trace the most recent change from approval to employee communication, payroll and the employee file. Fix any break in the process. | G14: A complete change record with approvals, required agreement or consultation and matching payroll instructions. | H14: Owner / HR lead | I14: Risk Method timing is the initial response target; actual duties and earlier events take precedence. Recheck: Each material change to employment terms. | J14: A current terms register and a controlled set of suitable templates can be proportionate. | K14: Use controlled templates, approval limits and version/variation tracking across entities and roles. | L14: Employment terms and engagement review, with legal referral for issues outside the agreed HR advisory scope. | M14: TERMS | N14: S25;S14 | O14: https://www.fairwork.gov.au/tools-and-resources/best-practice-guides/consultation-and-cooperation-in-the-workplace https://www.fairwork.gov.au/tools-and-resources/fact-sheets/rights-and-obligations/record-keeping-pay-slips | P14: 2 | Q14: Confirm required agreement or consultation, approval authority and the effective date. Send the approved instruction to payroll and the record owner. | R14: Check the first affected roster or payment and confirm the final record reflects the change. | S14: Assuming a variation letter proves that every required step occurred. | T14: Each material change to employment terms. | U14: PAY01;CON01
A15: A_REC01 | B15: REC01 | C15: Use REC01_0 / _1 / _2 / _3 / _DK in Answer Outcomes, then apply Risk Context. Weight is not the risk rating. | D15: Define the job before evaluating the person | E15: A vague role brief can produce a capable hire who is solving the wrong problem, with avoidable cost and early frustration. | F15: For your next vacancy, write the key outcomes, essential skills and responsibilities before drafting the advert or interview questions. | G15: An agreed role brief that the advert, selection criteria and initial performance goals reflect. | H15: Hiring manager | I15: Risk Method timing is the initial response target; actual duties and earlier events take precedence. Recheck: A new vacancy, changed service model or repeated early turnover. | J15: A one-page role brief and short interview record may be enough; an applicant-tracking system is not required. | K15: Use common criteria and decision records across interviewers, with monitored adjustments and data access. | L15: Role definition, selection guide and hiring-manager coaching. | M15: HIRING | N15: S01;S27 | O15: https://www.abs.gov.au/statistics/standards/abs-forms-design-standards/2023/general-forms-design-principles-question-structure https://www.fairwork.gov.au/sites/default/files/migration/711/managing-underperformance-best-practice-guide.pdf | P15: 2 | Q15: Agree the essential outcomes, requirements and boundaries with the person who will manage the role. | R15: Check that the advertisement, interview criteria and early performance expectations all use the same role brief. | S15: Writing a description around the departing employee rather than the work now required. | T15: A new vacancy, changed service model or repeated early turnover. | U15: None
A16: A_REC02 | B16: REC02 | C16: Use REC02_0 / _1 / _2 / _3 / _DK in Answer Outcomes, then apply Risk Context. Weight is not the risk rating. | D16: Make the selection decision explainable | E16: Inconsistent criteria or unsupported judgements can exclude suitable candidates and make a hiring decision difficult to explain. | F16: Use a short assessment guide for the next recruitment process. Agree the criteria before interviews and record the evidence behind the recommendation. | G16: A completed selection record and an appropriate applicant-information handling process. | H16: Hiring manager | I16: Risk Method timing is the initial response target; actual duties and earlier events take precedence. Recheck: A new hiring manager, selection tool or concern about a decision. | J16: A one-page role brief and short interview record may be enough; an applicant-tracking system is not required. | K16: Use common criteria and decision records across interviewers, with monitored adjustments and data access. | L16: Role definition, selection guide and hiring-manager coaching. | M16: HIRING | N16: S01;S15 | O16: https://www.abs.gov.au/statistics/standards/abs-forms-design-standards/2023/general-forms-design-principles-question-structure https://www.oaic.gov.au/privacy/privacy-guidance-for-organisations-and-government-agencies/organisations/employee-records-exemption | P16: 3 | Q16: Agree role-related criteria, appropriate adjustments and the evidence interviewers will record. Identify conflicts of interest. | R16: Compare the decision record with the evidence for the preferred candidate and review unexplained differences between interviewers. | S16: Equating consistency with identical questions when a candidate needs an appropriate adjustment. | T16: A new hiring manager, selection tool or concern about a decision. | U16: REC01
A17: A_REC03 | B17: REC03 | C17: Use REC03_0 / _1 / _2 / _3 / _DK in Answer Outcomes, then apply Risk Context. Weight is not the risk rating. | D17: Reduce surprises between offer and first day | E17: A difference between the advertised role and the actual work can undermine trust before a new employee has settled in. | F17: Compare the advert, interview discussion and offer for a recent hire. Ask where expectations could have been clearer and update the next hiring process. | G17: Consistent candidate information and a simple communication checklist. | H17: Hiring manager | I17: Risk Method timing is the initial response target; actual duties and earlier events take precedence. Recheck: Changed duties, work location or feedback from a recent starter. | J17: A one-page role brief and short interview record may be enough; an applicant-tracking system is not required. | K17: Use common criteria and decision records across interviewers, with monitored adjustments and data access. | L17: Role definition, selection guide and hiring-manager coaching. | M17: HIRING | N17: S01 | O17: https://www.abs.gov.au/statistics/standards/abs-forms-design-standards/2023/general-forms-design-principles-question-structure | P17: 2 | Q17: Align the advert, interview explanation and proposed terms. Explain genuine constraints such as hours, travel and decision authority. | R17: Ask a recent starter what differed from the recruitment discussion and correct misleading or incomplete information. | S17: Presenting only the attractive aspects of the role and leaving the constraints until the offer. | T17: Changed duties, work location or feedback from a recent starter. | U17: REC01;CON01
... A33: A_LND02 | B33: LND02 | C33: Use LND02_0 / _1 / _2 / _3 / _DK in Answer Outcomes, then apply Risk Context. Weight is not the risk rating. | D33: Check what changed after the training | E33: Attendance records do not show whether a person can apply a skill or whether the original problem improved. | F33: Choose a recent training activity and agree one observable result. Ask the manager and employee to review whether that result is now demonstrated. | G33: A follow-up example shows whether the intended work outcome improved, and any remaining support or corrective learning has been delivered and checked. | H33: Owner / people manager | I33: Risk Method timing is the initial response target; actual duties and earlier events take precedence. Recheck: Completion of material training or continuing errors despite training. | J33: One priority skill and one critical-task backup may be a sensible starting point. | K33: Use a role/capability view, application measures and cover for critical functions across teams. | L33: Focused capability planning, role development and critical-task cover. | M33: CAPABILITY | N33: S27 | O33: https://www.fairwork.gov.au/sites/default/files/migration/711/managing-underperformance-best-practice-guide.pdf | P33: 2 | Q33: Define the intended on-the-job change and provide an opportunity, resources and feedback to practise it. | R33: Observe the task or review a work outcome after learning; adjust the support where the change has not occurred. | S33: Buying more training when the obstacle is workload, unclear expectations or missing tools. | T33: Completion of material training or continuing errors despite training. | U33: LND01;PER01
A34: A_LND03 | B34: LND03 | C34: Use LND03_0 / _1 / _2 / _3 / _DK in Answer Outcomes, then apply Risk Context. Weight is not the risk rating. | D34: Reduce reliance on one person | E34: If essential work depends on one unavailable person, payroll, client delivery or approvals can stop even when the rest of the team is capable. | F34: Choose one business-critical task with no tested backup. Document the essentials and have the nominated backup perform a supervised run-through. | G34: A tested cover arrangement for priority tasks, including secure access and authorisations. | H34: Owner / people manager | I34: Risk Method timing is the initial response target; actual duties and earlier events take precedence. Recheck: Key leave, resignation, changed systems or a failed continuity test. | J34: One priority skill and one critical-task backup may be a sensible starting point. | K34: Use a role/capability view, application measures and cover for critical functions across teams. | L34: Focused capability planning, role development and critical-task cover. | M34: CAPABILITY | N34: DESIGN | P34: 3 | Q34: Name a capable backup or external alternative and prepare secure, usable instructions for the critical task. | R34: Test the backup without relying on the usual person. Record what failed and retest it. | S34: Assuming the key person can write instructions after becoming unavailable, or sharing their password. | T34: Key leave, resignation, changed systems or a failed continuity test. | U34: DAT03
A35: A_CUL01 | B35: CUL01 | C35: Use CUL01_0 / _1 / _2 / _3 / _DK in Answer Outcomes, then apply Risk Context. Weight is not the risk rating. | D35: Turn employee input into visible decisions | E35: Silence can hide concerns, and repeated requests for feedback without a response can discourage further input. | F35: Choose a proportionate listening method. Identify one or two priorities and tell employees what action will follow and when. | G35: Feedback has been considered, the business has communicated its response and the agreed priority action has been implemented and checked with employees. A survey or summary alone does not close the action. | H35: Business leader | I35: Risk Method timing is the initial response target; actual duties and earlier events take precedence. Recheck: Listening cycles, material change or evidence that people have stopped speaking up. | J35: Use direct conversations with a safe alternative for sensitive issues. Do not promise anonymity where individuals can be inferred. | K35: Combine employee listening with manager/site patterns and visible follow-through; protect confidentiality in small subgroups. | L35: Employee listening, retention diagnosis and accountable leadership practices. | M35: CULTURE | N35: S25;S10 | O35: https://www.fairwork.gov.au/tools-and-resources/best-practice-guides/consultation-and-cooperation-in-the-workplace https://humanrights.gov.au/resource-hub/resources-for-organisations-businesses/positive-duty-pdfs/guidelines-for-complying-with-the-positive-duty-under-the-sex-discrimination-act-1984-cth | P35: 2 | Q35: Choose a credible listening method appropriate to the team and explain confidentiality limitations and alternative reporting routes. | R35: Return to employees with what was heard, what will change and the reasons for decisions; check whether action addressed the issue. | S35: Promising anonymity in a small group where people can be identified. | T35: Listening cycles, material change or evidence that people have stopped speaking up. | U35: PSY04
A36: A_CUL02 | B36: CUL02 | C36: Use CUL02_0 / _1 / _2 / _3 / _DK in Answer Outcomes, then apply Risk Context. Weight is not the risk rating. | D36: Look beyond the turnover percentage | E36: Waiting for resignations can make preventable causes harder to address and increase disruption in critical roles. | F36: Review recent departures and key retention concerns. Check the evidence before deciding whether pay, leadership, workload or another factor needs attention. | G36: The business has tested the main retention concerns, implemented targeted actions and reviewed subsequent feedback and departures. Do not claim a causal reduction in turnover from a short observation period. | H36: Business leader | I36: Risk Method timing is the initial response target; actual duties and earlier events take precedence. Recheck: A key-person concern, repeated departures or a changed labour market. | J36: Use direct conversations with a safe alternative for sensitive issues. Do not promise anonymity where individuals can be inferred. | K36: Combine employee listening with manager/site patterns and visible follow-through; protect confidentiality in small subgroups. | L36: Employee listening, retention diagnosis and accountable leadership practices. | M36: CULTURE | N36: DESIGN | P36: 2 | Q36: Hold targeted retention conversations and compare themes with departures, workloads, manager practices and role expectations. | R36: Agree specific changes and revisit whether the reason for concern has improved. | S36: Treating every retention issue as a salary issue or relying on percentages from a very small team. | T36: A key-person concern, repeated departures or a changed labour market. | U36: CUL01;LND03
A37: A_CUL03 | B37: CUL03 | C37: Use CUL03_0 / _1 / _2 / _3 / _DK in Answer Outcomes, then apply Risk Context. Weight is not the risk rating. | D37: Make recognition fair and specific | E37: Inconsistent recognition can leave useful contributions overlooked and make access to development feel arbitrary. | F37: Review who received recognition or development opportunities recently and why. Address gaps and explain the criteria managers should use. | G37: Recognition and development decisions have been checked for consistency and access, identified barriers have been addressed, and a later example shows the revised approach in use. | H37: Business leader | I37: Risk Method timing is the initial response target; actual duties and earlier events take precedence. Recheck: Recognition cycles or concerns about unequal access to opportunities. | J37: Use direct conversations with a safe alternative for sensitive issues. Do not promise anonymity where individuals can be inferred. | K37: Combine employee listening with manager/site patterns and visible follow-through; protect confidentiality in small subgroups. | L37: Employee listening, retention diagnosis and accountable leadership practices. | M37: CULTURE | N37: S10;S11 | O37: https://humanrights.gov.au/resource-hub/resources-for-organisations-businesses/positive-duty-pdfs/guidelines-for-complying-with-the-positive-duty-under-the-sex-discrimination-act-1984-cth https://www.safeworkaustralia.gov.au/safety-topic/managing-health-and-safety/mental-health/managing-risks/identifying-assessing-controlling-and-reviewing | P37: 1 | Q37: Agree simple, explainable criteria for recognition and opportunity; check whose work is less visible because of role, location or hours. | R37: Review a later allocation for fairness and ask whether the recognition was meaningful. | S37: Using social-event participation or personal visibility as a proxy for contribution. | T37: Recognition cycles or concerns about unequal access to opportunities. | U37: CUL01
A38: A_CUL04 | B38: CUL04 | C38: Use CUL04_0 / _1 / _2 / _3 / _DK in Answer Outcomes, then apply Risk Context. Weight is not the risk rating. | D38: Make leadership behaviour part of performance | E38: A leader who delivers operational results can still create unresolved people problems unless behaviour is reviewed separately. | F38: Agree a small set of observable management expectations and a way to review them using more than the leader's own account. | G38: People-leadership expectations and support are clear, and a sample of real decisions demonstrates their use. Inconsistent behaviour is addressed and followed up, not simply recorded in a leadership document. | H38: Business leader | I38: Risk Method timing is the initial response target; actual duties and earlier events take precedence. Recheck: Repeated team concerns, a new leader or a performance review. | J38: Use direct conversations with a safe alternative for sensitive issues. Do not promise anonymity where individuals can be inferred. | K38: Combine employee listening with manager/site patterns and visible follow-through; protect confidentiality in small subgroups. | L38: Employee listening, retention diagnosis and accountable leadership practices. | M38: LEADERSHIP | N38: S10;S27 | O38: https://humanrights.gov.au/resource-hub/resources-for-organisations-businesses/positive-duty-pdfs/guidelines-for-complying-with-the-positive-duty-under-the-sex-discrimination-act-1984-cth https://www.fairwork.gov.au/sites/default/files/migration/711/managing-underperformance-best-practice-guide.pdf | P38: 2 | Q38: Set observable expectations for feedback, decisions, respectful conduct and follow-through, with support to meet them. | R38: Review actual examples and employee input, and address recurring concerns even where commercial results are strong. | S38: Rewarding outcomes while overlooking the conduct used to achieve them. | T38: Repeated team concerns, a new leader or a performance review. | U38: CUL01;PER01
A39: A_DAT01 | B39: DAT01 | C39: Use DAT01_0 / _1 / _2 / _3 / _DK in Answer Outcomes, then apply Risk Context. Weight is not the risk rating. | D39: Make the pay decision traceable | E39: Missing source records make it harder to establish what work was performed and whether entitlements were paid correctly. | F39: Choose a recent pay period and reconstruct one ordinary and one exception payment from source records. Identify missing records and fix the capture process. | G39: A reproducible pay trail, retention rules and records of corrections rather than unexplained changes. | H39: Payroll / systems lead | I39: Risk Method timing is the initial response target; actual duties and earlier events take precedence. Recheck: A discrepancy, record-system change or missing source record. | J39: A secure, organised repository with controlled access and tested recovery can be sufficient; a particular HR system is not required. | K39: Review role-based access, supplier arrangements, retention, logs and recovery across the employee lifecycle. | L39: Employment-record process review and coordination with privacy/cyber specialists where necessary. | M39: PAY_ASSURANCE | N39: S14;S07 | O39: https://www.fairwork.gov.au/tools-and-resources/fact-sheets/rights-and-obligations/record-keeping-pay-slips https://www.fairwork.gov.au/newsroom/news/offsetting-and-record-keeping-salaried-employees | P39: 3 | Q39: Identify missing records and improve capture, retention and correction controls without retrospectively inventing evidence. | R39: Repeat the reconstruction using an ordinary and an exception payment and confirm another authorised person can follow it. | S39: Treating the roster or payroll output as the complete record of actual work. | T39: A discrepancy, record-system change or missing source record. | U39: PAY01
A40: A_DAT02 | B40: DAT02 | C40: Use DAT02_0 / _1 / _2 / _3 / _DK in Answer Outcomes, then apply Risk Context. Weight is not the risk rating. | D40: Protect information across the whole process | E40: Excessive access or uncontrolled sharing can expose sensitive information, including material held outside the main HR system. | F40: Map where employee and applicant information is held and shared. Remove unnecessary access and check the basis for collection, use and retention. | G40: The information-handling and access review is complete, unnecessary access has been removed, applicable privacy and retention requirements are mapped and priority safeguards work in practice. An unresolved exposure stays open. | H40: Payroll / systems lead | I40: Risk Method timing is the initial response target; actual duties and earlier events take precedence. Recheck: New systems or providers, access changes or suspected disclosure. | J40: A secure, organised repository with controlled access and tested recovery can be sufficient; a particular HR system is not required. | K40: Review role-based access, supplier arrangements, retention, logs and recovery across the employee lifecycle. | L40: Employment-record process review and coordination with privacy/cyber specialists where necessary. | M40: INFORMATION | N40: S15;S16;S17 | O40: https://www.oaic.gov.au/privacy/privacy-guidance-for-organisations-and-government-agencies/organisations/employee-records-exemption https://www.oaic.gov.au/privacy/privacy-guidance-for-organisations-and-government-agencies/organisations/small-business https://www.oaic.gov.au/news/media-centre/new-resources-on-transparency-for-use-of-ai-and-automated-decision-making | P40: 3 | Q40: Map collection, storage, sharing and providers. Restrict unnecessary access and check applicable privacy, retention and incident requirements. | R40: Test a representative information flow and remove unnecessary copies or access through a controlled process, subject to retention and preservation requirements. | S40: Assuming the employee-records exemption covers applicants, external providers and every use of staff data. | T40: New systems or providers, access changes or suspected disclosure. | U40: None
A41: A_DAT03 | B41: DAT03 | C41: Use DAT03_0 / _1 / _2 / _3 / _DK in Answer Outcomes, then apply Risk Context. Weight is not the risk rating. | D41: Test retrieval before you need it | E41: A backup that cannot be retrieved by an authorised person may fail when the usual administrator or system is unavailable. | F41: Ask an authorised backup person to retrieve a defined set of current records without the usual administrator's assistance. Record and fix any gaps. | G41: A successful retrieval test, secure access arrangements and a record owner. | H41: Payroll / systems lead | I41: Risk Method timing is the initial response target; actual duties and earlier events take precedence. Recheck: System changes, administrator absence or a failed recovery test. | J41: A secure, organised repository with controlled access and tested recovery can be sufficient; a particular HR system is not required. | K41: Review role-based access, supplier arrangements, retention, logs and recovery across the employee lifecycle. | L41: Employment-record process review and coordination with privacy/cyber specialists where necessary. | M41: INFORMATION | N41: S14;S15 | O41: https://www.fairwork.gov.au/tools-and-resources/fact-sheets/rights-and-obligations/record-keeping-pay-slips https://www.oaic.gov.au/privacy/privacy-guidance-for-organisations-and-government-agencies/organisations/employee-records-exemption | P41: 3 | Q41: Arrange controlled backup access, current exports or recovery methods and clear ownership. | R41: Run a retrieval test using a defined set of essential records and verify completeness and current versions. | S41: Sharing passwords or assuming a supplier will provide a usable export immediately. | T41: System changes, administrator absence or a failed recovery test. | U41: DAT02
A42: A_EXT01 | B42: EXT01 | C42: Use EXT01_0 / _1 / _2 / _3 / _DK in Answer Outcomes, then apply Risk Context. Weight is not the risk rating. | D42: Review the decision before it becomes irreversible | E42: A decision can be difficult to reverse once communicated. A probation clause or notice payment does not resolve every legal protection or process requirement. | F42: Use a pre-decision review covering the reason, evidence, employee response, protected circumstances, alternatives and required procedure. Obtain advice for a live high-risk matter. | G42: A dated decision record with the applicable checks and approvals, prepared before the decision is communicated. | H42: Owner / HR lead | I42: Risk Method timing is the initial response target; actual duties and earlier events take precedence. Recheck: Any proposed employer-initiated termination or disputed exit. | J42: A short pre-decision and departure checklist with advice for a live high-risk matter can be proportionate. | K42: Separate decision approval, payroll checking, system access and handover ownership; test that the handovers work. | L42: Pre-decision HR review, final-pay coordination and legal referral where the matter requires it. | M42: FAIR_DECISIONS | N42: S02;S26 | O42: https://www.fairwork.gov.au/taxonomy/term/527 https://www.fairwork.gov.au/tools-and-resources/fact-sheets/minimum-workplace-entitlements/ending-employment | P42: 3 | Q42: Check the reason, relevant facts, response opportunity, protected circumstances and available alternatives before approving the decision. | R42: Have an appropriate reviewer test the reasoning and required process before communication, particularly for a live or contested matter. | S42: Choosing the exit outcome first and assembling the justification afterwards. | T42: Any proposed employer-initiated termination or disputed exit. | U42: None
A43: A_EXT02 | B43: EXT02 | C43: Use EXT02_0 / _1 / _2 / _3 / _DK in Answer Outcomes, then apply Risk Context. Weight is not the risk rating. | D43: Check final pay as a separate transaction | E43: Final pay can include rules and entitlements that do not appear in ordinary payroll and should be checked as a separate transaction. | F43: Use an exit payment checklist and independently review unusual notice, leave, redundancy or deduction items before processing. | G43: A completed final-pay calculation and review, with written employment documentation. | H43: Owner / HR lead | I43: Risk Method timing is the initial response target; actual duties and earlier events take precedence. Recheck: Every departure and any unusual exit payment. | J43: A short pre-decision and departure checklist with advice for a live high-risk matter can be proportionate. | K43: Separate decision approval, payroll checking, system access and handover ownership; test that the handovers work. | L43: Pre-decision HR review, final-pay coordination and legal referral where the matter requires it. | M43: EXIT | N43: S26;S08;S14 | O43: https://www.fairwork.gov.au/tools-and-resources/fact-sheets/minimum-workplace-entitlements/ending-employment https://www.fairwork.gov.au/pay-and-wages/deductions-and-related-issues/deducting-pay https://www.fairwork.gov.au/tools-and-resources/fact-sheets/rights-and-obligations/record-keeping-pay-slips | P43: 3 | Q43: Reconcile notice, leave, redundancy where relevant, deductions and timing against the actual exit circumstances. | R43: Retain the calculation, appropriate review and payment record; check that employment documentation matches the decision. | S43: Holding back final pay because equipment has not been returned without checking the lawful basis. | T43: Every departure and any unusual exit payment. | U43: PAY01;PAY03;EXT01
A44: A_EXT03 | B44: EXT03 | C44: Use EXT03_0 / _1 / _2 / _3 / _DK in Answer Outcomes, then apply Risk Context. Weight is not the risk rating. | D44: Close the operational gaps in an exit | E44: Late or incomplete offboarding can leave information accessible and essential work without an owner. | F44: Review your most recent exit against a short offboarding checklist, including systems outside the main HR platform. | G44: A completed offboarding record showing access, property, handover and record retention. | H44: Owner / HR lead | I44: Risk Method timing is the initial response target; actual duties and earlier events take precedence. Recheck: Any departure, particularly one involving privileged system access. | J44: A short pre-decision and departure checklist with advice for a live high-risk matter can be proportionate. | K44: Separate decision approval, payroll checking, system access and handover ownership; test that the handovers work. | L44: Pre-decision HR review, final-pay coordination and legal referral where the matter requires it. | M44: EXIT | N44: S14;S15;S08 | O44: https://www.fairwork.gov.au/tools-and-resources/fact-sheets/rights-and-obligations/record-keeping-pay-slips https://www.oaic.gov.au/privacy/privacy-guidance-for-organisations-and-government-agencies/organisations/employee-records-exemption https://www.fairwork.gov.au/pay-and-wages/deductions-and-related-issues/deducting-pay | P44: 3 | Q44: Coordinate access changes, record preservation, property and work handover with the actual departure circumstances. | R44: Confirm completion with systems and work owners, and test that essential information remains accessible to authorised staff. | S44: Deleting accounts or records before checking preservation requirements and transfer of work. | T44: Any departure, particularly one involving privileged system access. | U44: DAT02;DAT03
A45: A_PSY01 | B45: PSY01 | C45: Use PSY01_0 / _1 / _2 / _3 / _DK in Answer Outcomes, then apply Risk Context. Weight is not the risk rating. | D45: Identify what in the work could cause harm | E45: Without worker input and a review of actual work, workload, isolation, poor support or other hazards may remain unrecognised. | F45: Discuss the main work pressures and hazards with employees using a safe process. Record the work-related causes, who is exposed and what needs further assessment. | G45: A proportionate psychosocial hazard assessment informed by workers and relevant evidence. | H45: Business leader / safety lead | I45: Risk Method timing is the initial response target; actual duties and earlier events take precedence. Recheck: Changed work, worker concerns, incident patterns or control failure. | J45: A concise prevention and risk record, employee consultation and a credible alternative reporting route can be proportionate. | K45: Check work-design controls, manager accountability, reporting independence and monitoring across locations and workforce groups. | L45: Psychosocial/positive-duty assessment and prevention planning, with specialist WHS/legal input where appropriate. | M45: PSYCHOSOCIAL | N45: S11;S12 | O45: https://www.safeworkaustralia.gov.au/safety-topic/managing-health-and-safety/mental-health/managing-risks/identifying-assessing-controlling-and-reviewing https://www.safeworkaustralia.gov.au/safety-topic/managing-health-and-safety/mental-health/managing-risks/differences-between-whs-and-wellbeing | P45: 3 | Q45: Discuss relevant tasks and work conditions with workers and map the hazards, including how they can combine. | R45: Check whether identified hazards lead to practical control actions and revisit roles or settings omitted from the review. | S45: Waiting for a formal complaint or treating a wellbeing survey as the entire risk process. | T45: Changed work, worker concerns, incident patterns or control failure. | U45: None
A46: A_PSY02 | B46: PSY02 | C46: Use PSY02_0 / _1 / _2 / _3 / _DK in Answer Outcomes, then apply Risk Context. Weight is not the risk rating. | D46: Control the cause, not only the consequences | E46: Support after a problem does not replace controls addressing its work-related cause. Missing ownership can leave recognised risks unmanaged. | F46: Select the highest-priority work-related risk, agree a practical change to reduce exposure, assign an owner and set a review of effectiveness. | G46: A control record showing the change made and evidence about whether it is working. | H46: Business leader / safety lead | I46: Risk Method timing is the initial response target; actual duties and earlier events take precedence. Recheck: A changed hazard, ineffective control or recurrence of harm. | J46: A concise prevention and risk record, employee consultation and a credible alternative reporting route can be proportionate. | K46: Check work-design controls, manager accountability, reporting independence and monitoring across locations and workforce groups. | L46: Psychosocial/positive-duty assessment and prevention planning, with specialist WHS/legal input where appropriate. | M46: PSYCHOSOCIAL | N46: S11;S12 | O46: https://www.safeworkaustralia.gov.au/safety-topic/managing-health-and-safety/mental-health/managing-risks/identifying-assessing-controlling-and-reviewing https://www.safeworkaustralia.gov.au/safety-topic/managing-health-and-safety/mental-health/managing-risks/differences-between-whs-and-wellbeing | P46: 3 | Q46: Select proportionate changes to the work, staffing, supervision or other source of exposure and assign responsibility. | R46: Check with affected workers and operational evidence whether the control works; revise it where exposure remains. | S46: Using resilience training or an EAP as the main response to an excessive workload or unsafe work design. | T46: A changed hazard, ineffective control or recurrence of harm. | U46: PSY01
A47: A_PSY03 | B47: PSY03 | C47: Use PSY03_0 / _1 / _2 / _3 / _DK in Answer Outcomes, then apply Risk Context. Weight is not the risk rating. | D47: Make prevention visible in the way the business operates | E47: A policy or training session alone may not address where sex-related unlawful conduct could occur or how leaders prevent it. | F47: Review your approach against the AHRC standards, identify risks in your work settings and record proportionate preventative actions with leadership ownership. | G47: A prevention plan and implementation evidence covering the relevant AHRC standards, scaled to the business. | H47: Business leader / safety lead | I47: Risk Method timing is the initial response target; actual duties and earlier events take precedence. Recheck: Changed work, reported conduct, ineffective controls or a scheduled prevention review. | J47: A concise prevention and risk record, employee consultation and a credible alternative reporting route can be proportionate. | K47: Check work-design controls, manager accountability, reporting independence and monitoring across locations and workforce groups. | L47: Psychosocial/positive-duty assessment and prevention planning, with specialist WHS/legal input where appropriate. | M47: RESPECT | N47: S10 | O47: https://humanrights.gov.au/resource-hub/resources-for-organisations-businesses/positive-duty-pdfs/guidelines-for-complying-with-the-positive-duty-under-the-sex-discrimination-act-1984-cth | P47: 3 | Q47: Review relevant work situations and power imbalances, assign leadership accountability and implement proportionate prevention and reporting measures. | R47: Review whether measures are used and effective, including risks involving customers, contractors or influential employees. | S47: Assuming no complaint means prevention is working, or treating positive duty as a generic bullying policy. | T47: Changed work, reported conduct, ineffective controls or a scheduled prevention review. | U47: PSY01;PSY04
A48: A_PSY04 | B48: PSY04 | C48: Use PSY04_0 / _1 / _2 / _3 / _DK in Answer Outcomes, then apply Risk Context. Weight is not the risk rating. | D48: Make the reporting route work when power is involved | E48: A reporting route can fail precisely when the concern involves the person controlling it, leaving the business without a credible way to hear and address the issue. | F48: Identify who could receive a concern when the owner, manager or usual contact is involved, and whether that person has the authority and independence needed to arrange an appropriate response. | G48: Staff can identify and use a credible alternative route when the normal contact is involved, the recipient can arrange an appropriate response, and confidentiality and protection-from-retaliation safeguards have been tested. | H48: Business leader / safety lead | I48: Risk Method timing is the initial response target; actual duties and earlier events take precedence. Recheck: Changed ownership or reporting contacts, a conflict or concern about retaliation. | J48: A concise prevention and risk record, employee consultation and a credible alternative reporting route can be proportionate. | K48: Check work-design controls, manager accountability, reporting independence and monitoring across locations and workforce groups. | L48: Psychosocial/positive-duty assessment and prevention planning, with specialist WHS/legal input where appropriate. | M48: RESPECT | N48: S10;S11 | O48: https://humanrights.gov.au/resource-hub/resources-for-organisations-businesses/positive-duty-pdfs/guidelines-for-complying-with-the-positive-duty-under-the-sex-discrimination-act-1984-cth https://www.safeworkaustralia.gov.au/safety-topic/managing-health-and-safety/mental-health/managing-risks/identifying-assessing-controlling-and-reviewing | P48: 3 | Q48: Name an alternative recipient without a relevant conflict and document escalation, confidentiality boundaries and protection from retaliation. | R48: Explain the route to staff, test a fictional owner-related concern and check that the recipient can arrange an appropriate response. | S48: Naming another manager who still has to send every concern directly to the person complained about. | T48: Changed ownership or reporting contacts, a conflict or concern about retaliation. | U48: None
... A74: A_B25 | B74: B25 | C74: Use B25_0 / _1 / _2 / _3 / _DK in Answer Outcomes, then apply Risk Context. Weight is not the risk rating. | D74: Close the gaps between organisations sharing the work | E74: A worker can fall between organisations when each assumes the other manages induction, supervision, hazards or incident response. | F74: List the shared tasks and responsible organisations, then check with the worker where induction, supervision or reporting responsibilities are unclear. | G74: An agreed responsibility record, worker induction and consultation evidence, task-specific controls and a tested incident handover. | H74: Operational lead with the other duty holder | I74: Risk Method timing is the initial response target; actual duties and earlier events take precedence. Recheck: A new placement, changed task, site or shared-work arrangement. | J74: Use a concise record with a named owner and a practical check. The outcome matters more than the size of the document. | K74: Check each materially different work arrangement, team or location and specify handovers and escalation. | L74: A targeted review of the flagged issue, practical implementation support and specialist referral where necessary. | M74: SHARED_SAFETY | N74: S42;S13;S38 | O74: https://www.safeworkaustralia.gov.au/safety-topic/managing-health-and-safety/labour-hire/whs-duties https://www.safeworkaustralia.gov.au/safety-topic/managing-health-and-safety/identify-assess-and-control-hazards/managing-risks https://www.safeworkaustralia.gov.au/workers-compensation | P74: 3 | Q74: Agree who performs each safety task with the other duty holder and the worker, without treating the arrangement as a transfer of legal duties. | R74: Check the induction, actual task allocation, controls and incident handover before relying on the arrangement. | S74: Assuming the labour-hire provider or host carries every duty because of the contract. | T74: A new placement, changed task, site or shared-work arrangement. | U74: WHS01;WHS02;B13

Sheet Answer Outcomes
A1: Answer outcomes | risk, reasoning and next steps
A2: 345 complete answer pathways. No answer receives a compliance certificate. Unknowns produce verification tasks; a strong answer produces maintenance, not an invented problem. Apply live-matter overrides after this lookup.
A3: DREAMSTONEHR | PROPOSED V3.0 | 10 OCTOBER 2026
A5: Outcome ID | B5: Question ID | C5: Response code | D5: Selected response | E5: Finding headline | F5: What this answer establishes | G5: Why it matters | H5: Risk type | I5: Consequence class | J5: Base risk rank | K5: Base priority rank | L5: Why this rating | M5: First action | N5: Then implement | O5: Then verify | P5: Timing rule | Q5: Completion evidence | R5: Evidence to inspect | S5: Recheck trigger | T5: Suggested owner | U5: Optional support | V5: Action family | W5: Action ID | X5: Source IDs | Y5: Primary source URLs | Z5: Common trap
A6: PAY01_0 | B6: PAY01 | C6: 0 | D6: We have not checked which rules apply to our roles. | E6: Establish the rules behind your pay decisions | F6: The selected response reports a missing or unestablished element. Confirm the affected arrangements before drawing a conclusion about any actual breach or harm. | G6: An incorrect coverage or classification decision can affect pay, leave and working conditions every time the role is paid. | H6: Pay and employment rights | I6: 3 | J6: 3 | K6: 3 | L6: High provisional concern: an essential element remains unresolved. An incorrect coverage or classification decision can affect pay, leave and working conditions every time the role is paid. | M6: List each distinct role, actual duties, employment type, instrument and classification. Resolve uncertain roles before relying on the payroll settings. | N6: Compare actual duties with the relevant coverage and classification provisions. Record the reasoning and refer unresolved cases for competent review. | O6: Check that the approved outcome matches payroll and contract records. Review comparable roles if one classification was wrong. | P6: Review or verify within two business days and before the next affected event if earlier. Do not wait where a duty or current harm requires earlier action. | Q6: A dated coverage and classification record with reasons for every distinct role, appropriate review of uncertain classifications, and resulting payroll changes checked. An unresolved classification remains an open task. Confirm that the change works in practice, not only that a document exists. | R6: A dated coverage and classification record with reasons for every distinct role, appropriate review of uncertain classifications, and resulting payroll changes checked. An unresolved classification remains an open task. | S6: A changed role, new instrument or classification change. | T6: Payroll lead / owner | U6: Targeted payroll, award/classification or salary-arrangement review, scoped to the flagged population. | V6: PAY_ASSURANCE | W6: A_PAY01 | X6: S06;S14;DESIGN | Y6: https://www.fairwork.gov.au/pay-and-wages/minimum-wages/annualised-salaries https://www.fairwork.gov.au/tools-and-resources/fact-sheets/rights-and-obligations/record-keeping-pay-slips | Z6: A familiar job title, an ABN or an above-award salary is not evidence of correct coverage.
A7: PAY01_1 | B7: PAY01 | C7: 1 | D7: We rely on job titles, past practice or payroll defaults, without a recorded coverage check. | E7: Establish the rules behind your pay decisions | F7: The selected response relies on assumptions, informal decisions or an inconsistent process. The action is to make the relevant check reliable in routine work. | G7: An incorrect coverage or classification decision can affect pay, leave and working conditions every time the role is paid. | H7: Pay and employment rights | I7: 3 | J7: 3 | K7: 3 | L7: High provisional concern: an essential element remains unresolved. An incorrect coverage or classification decision can affect pay, leave and working conditions every time the role is paid. | M7: Replace the assumption with a current check. List each distinct role, actual duties, employment type, instrument and classification. Resolve uncertain roles before relying on the payroll settings. | N7: Compare actual duties with the relevant coverage and classification provisions. Record the reasoning and refer unresolved cases for competent review. | O7: Check that the approved outcome matches payroll and contract records. Review comparable roles if one classification was wrong. | P7: Review or verify within two business days and before the next affected event if earlier. Do not wait where a duty or current harm requires earlier action. | Q7: A dated coverage and classification record with reasons for every distinct role, appropriate review of uncertain classifications, and resulting payroll changes checked. An unresolved classification remains an open task. Confirm that the change works in practice, not only that a document exists. | R7: A dated coverage and classification record with reasons for every distinct role, appropriate review of uncertain classifications, and resulting payroll changes checked. An unresolved classification remains an open task. | S7: A changed role, new instrument or classification change. | T7: Payroll lead / owner | U7: Targeted payroll, award/classification or salary-arrangement review, scoped to the flagged population. | V7: PAY_ASSURANCE | W7: A_PAY01 | X7: S06;S14;DESIGN | Y7: https://www.fairwork.gov.au/pay-and-wages/minimum-wages/annualised-salaries https://www.fairwork.gov.au/tools-and-resources/fact-sheets/rights-and-obligations/record-keeping-pay-slips | Z7: A familiar job title, an ABN or an above-award salary is not evidence of correct coverage.
A8: PAY01_2 | B8: PAY01 | C8: 2 | D8: We have checked some roles, but changes or exceptions remain unresolved. | E8: Complete the remaining check: establish the rules behind your pay decisions | F8: The selected response identifies an incomplete element within an existing practice. Keep what works and target the unresolved part; the stronger elements do not cancel the gap. | G8: An incorrect coverage or classification decision can affect pay, leave and working conditions every time the role is paid. | H8: Pay and employment rights | I8: 3 | J8: 3 | K8: 3 | L8: High provisional concern: an essential element remains unresolved. An incorrect coverage or classification decision can affect pay, leave and working conditions every time the role is paid. | M8: Focus on the unresolved arrangements or exceptions. List each distinct role, actual duties, employment type, instrument and classification. Resolve uncertain roles before relying on the payroll settings. | N8: Compare actual duties with the relevant coverage and classification provisions. Record the reasoning and refer unresolved cases for competent review. | O8: Check that the approved outcome matches payroll and contract records. Review comparable roles if one classification was wrong. | P8: Review or verify within two business days and before the next affected event if earlier. Do not wait where a duty or current harm requires earlier action. | Q8: A dated coverage and classification record with reasons for every distinct role, appropriate review of uncertain classifications, and resulting payroll changes checked. An unresolved classification remains an open task. Confirm that the change works in practice, not only that a document exists. | R8: A dated coverage and classification record with reasons for every distinct role, appropriate review of uncertain classifications, and resulting payroll changes checked. An unresolved classification remains an open task. | S8: A changed role, new instrument or classification change. | T8: Payroll lead / owner | U8: Targeted payroll, award/classification or salary-arrangement review, scoped to the flagged population. | V8: PAY_ASSURANCE | W8: A_PAY01 | X8: S06;S14;DESIGN | Y8: https://www.fairwork.gov.au/pay-and-wages/minimum-wages/annualised-salaries https://www.fairwork.gov.au/tools-and-resources/fact-sheets/rights-and-obligations/record-keeping-pay-slips | Z8: A familiar job title, an ABN or an above-award salary is not evidence of correct coverage.
A9: PAY01_3 | B9: PAY01 | C9: 3 | D9: We have a current record for every role, including the basis for any award-free classification, and review it when duties change. | E9: Maintain and test: establish the rules behind your pay decisions | F9: The selected response reports an established and checked practice. The tool has not inspected the evidence and cannot certify the absence of risk. | G9: An incorrect coverage or classification decision can affect pay, leave and working conditions every time the role is paid. | H9: Pay and employment rights | I9: 3 | J9: 1 | K9: 1 | L9: Lower reported concern, not a finding of no risk. The assumed controls are self-reported; a current incident, contrary evidence or failed control takes precedence. | M9: Maintain the practice described. At the next relevant review, check that the approved outcome matches payroll and contract records. Review comparable roles if one classification was wrong. | N9: Check whether changes in work, people or applicable requirements have made the original process less reliable. | O9: Retain the review outcome and act on any new exception. An unresolved live issue overrides this maintenance pathway. | P9: Maintain at the stated trigger; for a new low-priority improvement, plan within 90 days. | Q9: A current example of the practice and a proportionate recheck record. A dated coverage and classification record with reasons for every distinct role, appropriate review of uncertain classifications, and resulting payroll changes checked. An unresolved classification remains an open task. | R9: A dated coverage and classification record with reasons for every distinct role, appropriate review of uncertain classifications, and resulting payroll changes checked. An unresolved classification remains an open task. | S9: A changed role, new instrument or classification change. | T9: Payroll lead / owner | U9: No further purchase is implied by this result. Seek support only for a material change, unresolved exception or chosen improvement. | V9: PAY_ASSURANCE | W9: A_PAY01 | X9: S06;S14;DESIGN | Y9: https://www.fairwork.gov.au/pay-and-wages/minimum-wages/annualised-salaries https://www.fairwork.gov.au/tools-and-resources/fact-sheets/rights-and-obligations/record-keeping-pay-slips | Z9: A familiar job title, an ABN or an above-award salary is not evidence of correct coverage.
A10: PAY01_DK | B10: PAY01 | C10: DK | D10: I need to confirm this. | E10: Verify: establish the rules behind your pay decisions | F10: This answer identifies a knowledge gap. It does not establish that the practice is missing, that harm has occurred or that a legal duty has been breached. | G10: An incorrect coverage or classification decision can affect pay, leave and working conditions every time the role is paid. | H10: Pay and employment rights | I10: 3 | J10: 0 | K10: 3 | L10: The risk is not rated from an unknown answer. Verification is High priority because: An incorrect coverage or classification decision can affect pay, leave and working conditions every time the role is paid. | M10: Ask the payroll lead / owner to show a current example of the process and the evidence listed below. Confirm the answer before deciding what must be repaired. | N10: Compare the example with the established-practice description: We have a current record for every role, including the basis for any award-free classification, and review it when duties change. | O10: Record what was checked, by whom and when. If it remains unclear, keep the verification task open and agree any proportionate interim safeguard. | P10: Review or verify within two business days and before the next affected event if earlier. Do not wait where a duty or current harm requires earlier action. | Q10: A dated verification record, the supporting example, an updated answer and any remaining action. No automatic compliance conclusion. | R10: A dated coverage and classification record with reasons for every distinct role, appropriate review of uncertain classifications, and resulting payroll changes checked. An unresolved classification remains an open task. | S10: A changed role, new instrument or classification change. | T10: Payroll lead / owner | U10: Targeted payroll, award/classification or salary-arrangement review, scoped to the flagged population. | V10: PAY_ASSURANCE | W10: A_PAY01 | X10: S06;S14;DESIGN | Y10: https://www.fairwork.gov.au/pay-and-wages/minimum-wages/annualised-salaries https://www.fairwork.gov.au/tools-and-resources/fact-sheets/rights-and-obligations/record-keeping-pay-slips | Z10: A familiar job title, an ABN or an above-award salary is not evidence of correct coverage.
A11: PAY02_0 | B11: PAY02 | C11: 0 | D11: We have not checked payroll against actual work and applicable rules. | E11: Test the payroll result, not just the base rate | F11: The selected response reports a missing or unestablished element. Confirm the affected arrangements before drawing a conclusion about any actual breach or harm. | G11: An unchecked pay rule can repeat across pay periods and employees. The initial gap is lack of assurance, not proof of an underpayment. | H11: Pay and employment rights | I11: 3 | J11: 3 | K11: 3 | L11: High provisional concern: an essential element remains unresolved. An unchecked pay rule can repeat across pay periods and employees. The initial gap is lack of assurance, not proof of an underpayment. | M11: Select representative ordinary and exception pay periods and obtain the actual work records, applicable rules and payslips. Define the arrangements being checked before calculating any difference. | N11: Recalculate selected ordinary and exception pay periods using actual work records. Record differences by entitlement, period and affected arrangement. | O11: Investigate the cause of each difference, extend the review where appropriate and test the next affected pay run after correction. | P11: Review or verify within two business days and before the next affected event if earlier. Do not wait where a duty or current harm requires earlier action. | Q11: A dated pay-check record for each materially different pay arrangement, with discrepancies investigated, required corrections completed and the next affected pay run checked. Keep any unresolved scope or payment issue open. Confirm that the change works in practice, not only that a document exists. | R11: A dated pay-check record for each materially different pay arrangement, with discrepancies investigated, required corrections completed and the next affected pay run checked. Keep any unresolved scope or payment issue open. | S11: A pay-rule change, payroll migration, discrepancy or new work pattern. | T11: Payroll lead / owner | U11: Targeted payroll, award/classification or salary-arrangement review, scoped to the flagged population. | V11: PAY_ASSURANCE | W11: A_PAY02 | X11: S06;S07;S14;DESIGN | Y11: https://www.fairwork.gov.au/pay-and-wages/minimum-wages/annualised-salaries https://www.fairwork.gov.au/newsroom/news/offsetting-and-record-keeping-salaried-employees https://www.fairwork.gov.au/tools-and-resources/fact-sheets/rights-and-obligations/record-keeping-pay-slips | Z11: A clean payroll report only shows that the system processed its current settings.
A12: PAY02_1 | B12: PAY02 | C12: 1 | D12: We assume our software, payroll provider or above-award rates make the payments correct. | E12: Test the payroll result, not just the base rate | F12: The selected response relies on assumptions, informal decisions or an inconsistent process. The action is to make the relevant check reliable in routine work. | G12: An unchecked pay rule can repeat across pay periods and employees. The initial gap is lack of assurance, not proof of an underpayment. | H12: Pay and employment rights | I12: 3 | J12: 3 | K12: 3 | L12: High provisional concern: an essential element remains unresolved. An unchecked pay rule can repeat across pay periods and employees. The initial gap is lack of assurance, not proof of an underpayment. | M12: Replace the assumption with a current check. Select representative ordinary and exception pay periods and obtain the actual work records, applicable rules and payslips. Define the arrangements being checked before calculating any difference. | N12: Recalculate selected ordinary and exception pay periods using actual work records. Record differences by entitlement, period and affected arrangement. | O12: Investigate the cause of each difference, extend the review where appropriate and test the next affected pay run after correction. | P12: Review or verify within two business days and before the next affected event if earlier. Do not wait where a duty or current harm requires earlier action. | Q12: A dated pay-check record for each materially different pay arrangement, with discrepancies investigated, required corrections completed and the next affected pay run checked. Keep any unresolved scope or payment issue open. Confirm that the change works in practice, not only that a document exists. | R12: A dated pay-check record for each materially different pay arrangement, with discrepancies investigated, required corrections completed and the next affected pay run checked. Keep any unresolved scope or payment issue open. | S12: A pay-rule change, payroll migration, discrepancy or new work pattern. | T12: Payroll lead / owner | U12: Targeted payroll, award/classification or salary-arrangement review, scoped to the flagged population. | V12: PAY_ASSURANCE | W12: A_PAY02 | X12: S06;S07;S14;DESIGN | Y12: https://www.fairwork.gov.au/pay-and-wages/minimum-wages/annualised-salaries https://www.fairwork.gov.au/newsroom/news/offsetting-and-record-keeping-salaried-employees https://www.fairwork.gov.au/tools-and-resources/fact-sheets/rights-and-obligations/record-keeping-pay-slips | Z12: A clean payroll report only shows that the system processed its current settings.
A13: PAY02_2 | B13: PAY02 | C13: 2 | D13: We check base rates, but some working patterns or other entitlements have not been tested. | E13: Complete the remaining check: test the payroll result, not just the base rate | F13: The selected response identifies an incomplete element within an existing practice. Keep what works and target the unresolved part; the stronger elements do not cancel the gap. | G13: An unchecked pay rule can repeat across pay periods and employees. The initial gap is lack of assurance, not proof of an underpayment. | H13: Pay and employment rights | I13: 3 | J13: 3 | K13: 3 | L13: High provisional concern: an essential element remains unresolved. An unchecked pay rule can repeat across pay periods and employees. The initial gap is lack of assurance, not proof of an underpayment. | M13: Focus on the unresolved arrangements or exceptions. Select representative ordinary and exception pay periods and obtain the actual work records, applicable rules and payslips. Define the arrangements being checked before calculating any difference. | N13: Recalculate selected ordinary and exception pay periods using actual work records. Record differences by entitlement, period and affected arrangement. | O13: Investigate the cause of each difference, extend the review where appropriate and test the next affected pay run after correction. | P13: Review or verify within two business days and before the next affected event if earlier. Do not wait where a duty or current harm requires earlier action. | Q13: A dated pay-check record for each materially different pay arrangement, with discrepancies investigated, required corrections completed and the next affected pay run checked. Keep any unresolved scope or payment issue open. Confirm that the change works in practice, not only that a document exists. | R13: A dated pay-check record for each materially different pay arrangement, with discrepancies investigated, required corrections completed and the next affected pay run checked. Keep any unresolved scope or payment issue open. | S13: A pay-rule change, payroll migration, discrepancy or new work pattern. | T13: Payroll lead / owner | U13: Targeted payroll, award/classification or salary-arrangement review, scoped to the flagged population. | V13: PAY_ASSURANCE | W13: A_PAY02 | X13: S06;S07;S14;DESIGN | Y13: https://www.fairwork.gov.au/pay-and-wages/minimum-wages/annualised-salaries https://www.fairwork.gov.au/newsroom/news/offsetting-and-record-keeping-salaried-employees https://www.fairwork.gov.au/tools-and-resources/fact-sheets/rights-and-obligations/record-keeping-pay-slips | Z13: A clean payroll report only shows that the system processed its current settings.
A14: PAY02_3 | B14: PAY02 | C14: 3 | D14: We check representative actual pay periods against applicable rules, document exceptions and verify that corrections are completed. | E14: Maintain and test: test the payroll result, not just the base rate | F14: The selected response reports an established and checked practice. The tool has not inspected the evidence and cannot certify the absence of risk. | G14: An unchecked pay rule can repeat across pay periods and employees. The initial gap is lack of assurance, not proof of an underpayment. | H14: Pay and employment rights | I14: 3 | J14: 1 | K14: 1 | L14: Lower reported concern, not a finding of no risk. The assumed controls are self-reported; a current incident, contrary evidence or failed control takes precedence. | M14: Maintain the practice described. At the next relevant review, investigate the cause of each difference, extend the review where appropriate and test the next affected pay run after correction. | N14: Check whether changes in work, people or applicable requirements have made the original process less reliable. | O14: Retain the review outcome and act on any new exception. An unresolved live issue overrides this maintenance pathway. | P14: Maintain at the stated trigger; for a new low-priority improvement, plan within 90 days. | Q14: A current example of the practice and a proportionate recheck record. A dated pay-check record for each materially different pay arrangement, with discrepancies investigated, required corrections completed and the next affected pay run checked. Keep any unresolved scope or payment issue open. | R14: A dated pay-check record for each materially different pay arrangement, with discrepancies investigated, required corrections completed and the next affected pay run checked. Keep any unresolved scope or payment issue open. | S14: A pay-rule change, payroll migration, discrepancy or new work pattern. | T14: Payroll lead / owner | U14: No further purchase is implied by this result. Seek support only for a material change, unresolved exception or chosen improvement. | V14: PAY_ASSURANCE | W14: A_PAY02 | X14: S06;S07;S14;DESIGN | Y14: https://www.fairwork.gov.au/pay-and-wages/minimum-wages/annualised-salaries https://www.fairwork.gov.au/newsroom/news/offsetting-and-record-keeping-salaried-employees https://www.fairwork.gov.au/tools-and-resources/fact-sheets/rights-and-obligations/record-keeping-pay-slips | Z14: A clean payroll report only shows that the system processed its current settings.
A15: PAY02_DK | B15: PAY02 | C15: DK | D15: I need to confirm this. | E15: Verify: test the payroll result, not just the base rate | F15: This answer identifies a knowledge gap. It does not establish that the practice is missing, that harm has occurred or that a legal duty has been breached. | G15: An unchecked pay rule can repeat across pay periods and employees. The initial gap is lack of assurance, not proof of an underpayment. | H15: Pay and employment rights | I15: 3 | J15: 0 | K15: 3 | L15: The risk is not rated from an unknown answer. Verification is High priority because: An unchecked pay rule can repeat across pay periods and employees. The initial gap is lack of assurance, not proof of an underpayment. | M15: Ask the payroll lead / owner to show a current example of the process and the evidence listed below. Confirm the answer before deciding what must be repaired. | N15: Compare the example with the established-practice description: We check representative actual pay periods against applicable rules, document exceptions and verify that corrections are completed. | O15: Record what was checked, by whom and when. If it remains unclear, keep the verification task open and agree any proportionate interim safeguard. | P15: Review or verify within two business days and before the next affected event if earlier. Do not wait where a duty or current harm requires earlier action. | Q15: A dated verification record, the supporting example, an updated answer and any remaining action. No automatic compliance conclusion. | R15: A dated pay-check record for each materially different pay arrangement, with discrepancies investigated, required corrections completed and the next affected pay run checked. Keep any unresolved scope or payment issue open. | S15: A pay-rule change, payroll migration, discrepancy or new work pattern. | T15: Payroll lead / owner | U15: Targeted payroll, award/classification or salary-arrangement review, scoped to the flagged population. | V15: PAY_ASSURANCE | W15: A_PAY02 | X15: S06;S07;S14;DESIGN | Y15: https://www.fairwork.gov.au/pay-and-wages/minimum-wages/annualised-salaries https://www.fairwork.gov.au/newsroom/news/offsetting-and-record-keeping-salaried-employees https://www.fairwork.gov.au/tools-and-resources/fact-sheets/rights-and-obligations/record-keeping-pay-slips | Z15: A clean payroll report only shows that the system processed its current settings.
A16: PAY03_0 | B16: PAY03 | C16: 0 | D16: Leave is handled without a consistent check of eligibility, balances or pay. | E16: Check leave against the person and their circumstances | F16: The selected response reports a missing or unestablished element. Confirm the affected arrangements before drawing a conclusion about any actual breach or harm. | G16: Incorrect accruals or leave payments can deprive employees of entitlements and distort the business's leave liability. | H16: Pay and employment rights | I16: 3 | J16: 3 | K16: 3 | L16: High provisional concern: an essential element remains unresolved. Incorrect accruals or leave payments can deprive employees of entitlements and distort the business's leave liability. | M16: Reconcile a sample of leave balances and payments to ordinary hours, service and the applicable rules. Record which exceptions need specialist checking. | N16: Check accrual and payment rules for relevant employment types and changes in hours or service. Reconcile opening balances and adjustments. | O16: Resolve differences, retain the calculation trail and check a later leave transaction against the corrected rule. | P16: Review or verify within two business days and before the next affected event if earlier. Do not wait where a duty or current harm requires earlier action. | Q16: A dated leave reconciliation against the applicable rules, with incorrect balances or payments corrected and a follow-up transaction checked. State-based and instrument-specific matters are resolved or remain clearly open. Confirm that the change works in practice, not only that a document exists. | R16: A dated leave reconciliation against the applicable rules, with incorrect balances or payments corrected and a follow-up transaction checked. State-based and instrument-specific matters are resolved or remain clearly open. | S16: Changed hours, service milestones, an instrument change or a leave discrepancy. | T16: Payroll lead / owner | U16: Targeted payroll, award/classification or salary-arrangement review, scoped to the flagged population. | V16: LEAVE | W16: A_PAY03 | X16: S14;S21;S28;S31;S39;DESIGN | Y16: https://www.fairwork.gov.au/tools-and-resources/fact-sheets/rights-and-obligations/record-keeping-pay-slips https://www.fairwork.gov.au/tools-and-resources/fact-sheets/minimum-workplace-entitlements/family-and-domestic-violence-leave https://www.fairwork.gov.au/leave/annual-leave/cashing-out-annual-leave https://www.nsw.gov.au/employment/rights-responsibilities/portable-long-service/csi-long-service-leave-scheme/employer-obligations https://www.fairwork.gov.au/employment-conditions/national-employment-standards | Z16: A balance that looks plausible is not the same as a reconciled balance.
